{"EstimationModel":"eucp_lm","SizeMetric":"EUCP","TransactionMetric":"SWTI","Effort":"7.02","UseCases":[{"Name":"Admin Analysts maintainer","_id":"EAID_1A34039C_4F37_4d3b_925E_C8F6DFB50318","SizeMeasurement":"0.00","feasible":true,"Personnel_UI":"50.00%","Personnel_DB":"25.00%","Personnel_FS":"25.00%","Personnel":3,"Duration":"0.00","Effort":"0.00","useCasePMEffort":"-1.00","useCaseDEVEffort":"-1.00","synthesizedEffort":"0.00","BusinessValue":0,"BVEffortRatio":"0.00"},{"Name":"Banks","_id":"EAID_08C5FF42_30EA_4365_90A4_FE99B05D1579","SizeMeasurement":"0.00","feasible":true,"Personnel_UI":"50.00%","Personnel_DB":"25.00%","Personnel_FS":"25.00%","Personnel":3,"Duration":"0.00","Effort":"0.00","useCasePMEffort":"-1.00","useCaseDEVEffort":"-1.00","synthesizedEffort":"0.00","BusinessValue":0,"BVEffortRatio":"0.00"},{"Name":"CleintIEric Lev)","_id":"EAID_3A13C330_D224_45a3_8AFB_E31D58F5A0BF","SizeMeasurement":"0.00","feasible":true,"Personnel_UI":"50.00%","Personnel_DB":"25.00%","Personnel_FS":"25.00%","Personnel":3,"Duration":"0.00","Effort":"0.00","useCasePMEffort":"-1.00","useCaseDEVEffort":"-1.00","synthesizedEffort":"0.00","BusinessValue":0,"BVEffortRatio":"0.00"},{"Name":"Financial analysis","_id":"EAID_1D5063A1_A7D2_479e_9654_CFF1AC694BA0","SizeMeasurement":"0.00","feasible":true,"Personnel_UI":"50.00%","Personnel_DB":"25.00%","Personnel_FS":"25.00%","Personnel":3,"Duration":"0.00","Effort":"0.00","useCasePMEffort":"-1.00","useCaseDEVEffort":"-1.00","synthesizedEffort":"0.00","BusinessValue":0,"BVEffortRatio":"0.00"},{"Name":"Investors","_id":"EAID_00C1476E_E201_4fa4_9E9C_3772F902219A","SizeMeasurement":"0.00","feasible":true,"Personnel_UI":"50.00%","Personnel_DB":"25.00%","Personnel_FS":"25.00%","Personnel":3,"Duration":"0.00","Effort":"0.00","useCasePMEffort":"-1.00","useCaseDEVEffort":"-1.00","synthesizedEffort":"0.00","BusinessValue":0,"BVEffortRatio":"0.00"},{"Name":"Real Estate Entrepreneurs","_id":"EAID_883DE236_FF62_49d3_A97C_8519AD26846B","SizeMeasurement":"0.00","feasible":true,"Personnel_UI":"50.00%","Personnel_DB":"25.00%","Personnel_FS":"25.00%","Personnel":3,"Duration":"0.00","Effort":"0.00","useCasePMEffort":"-1.00","useCaseDEVEffort":"-1.00","synthesizedEffort":"0.00","BusinessValue":0,"BVEffortRatio":"0.00"},{"Name":"Real Estate developers","_id":"EAID_8C207C7A_DAB4_4f40_9F06_48CA156915A4","SizeMeasurement":"0.00","feasible":true,"Personnel_UI":"50.00%","Personnel_DB":"25.00%","Personnel_FS":"25.00%","Personnel":3,"Duration":"0.00","Effort":"0.00","useCasePMEffort":"-1.00","useCaseDEVEffort":"-1.00","synthesizedEffort":"0.00","BusinessValue":0,"BVEffortRatio":"0.00"},{"Name":"Reasl estate brokers","_id":"EAID_07343A44_BE77_4fe8_9BB7_F901A8A29918","SizeMeasurement":"0.00","feasible":true,"Personnel_UI":"50.00%","Personnel_DB":"25.00%","Personnel_FS":"25.00%","Personnel":3,"Duration":"0.00","Effort":"0.00","useCasePMEffort":"-1.00","useCaseDEVEffort":"-1.00","synthesizedEffort":"0.00","BusinessValue":0,"BVEffortRatio":"0.00"}],"DomainModel":{"MVCEstimates":{"ViewEffort":"0.00","ModelEffort":"0.00","ControlEffort":"0.00"}},"SizeMeasurement":"1.00","feasible":true,"Personnel":1,"Duration":"1.00","HoursPerMonth":152,"Personnel_UI":"50.00%","Personnel_DB":"25.00%","Personnel_FS":"25.00%","TotalSynthesizedEffort":0,"EstimationResultsFile":"estimationResultEUCP.json"}