[{"Nodes":[{"Type":"activity","Name":"fork","_id":"EAID_1786B25E_D00D_4594_921F_04BA17E27C67","Stimulus":true,"OutScope":false},{"Type":"activity","Name":"Validate User Information","_id":"EAID_DD237FDE_EE4D_4fad_B594_47DE1792DC51","Stimulus":true,"OutScope":false}],"OutScope":false,"PathStr":"","pathLength":0,"avgDegree":0,"archDiff":0,"boundaryNum":0,"controlNum":0,"entityNum":0,"actorNum":0,"FPAnalytics":{"Operations":{},"Functional":["FUNC_NA"],"FunctionalTag":"FUNC_NA"},"TransactionAnalytics":{"Transactional":["TRAN_NA"],"TransactionalTag":"TRAN_NA","TranLength":2,"TotalDegree":2},"utw":4},{"Nodes":[{"Type":"activity","Name":"fork","_id":"EAID_1786B25E_D00D_4594_921F_04BA17E27C67","Stimulus":true,"OutScope":false},{"Type":"activity","Name":"Input Username and Password","_id":"EAID_FC7B0E7C_172B_4612_98DC_7BBA0C7C0E55","Stimulus":false,"OutScope":false,"Group":"System"},{"Type":"activity","Name":"Validate User Information","_id":"EAID_DD237FDE_EE4D_4fad_B594_47DE1792DC51","Stimulus":true,"OutScope":false}],"OutScope":false,"PathStr":"","pathLength":0,"avgDegree":0,"archDiff":0,"boundaryNum":0,"controlNum":0,"entityNum":0,"actorNum":0,"FPAnalytics":{"Operations":{},"Functional":["FUNC_NA"],"FunctionalTag":"FUNC_NA"},"TransactionAnalytics":{"Transactional":["TRAN_NA"],"TransactionalTag":"TRAN_NA","TranLength":3,"TotalDegree":3},"utw":4},{"Nodes":[{"Type":"activity","Name":"ActivityInitial","_id":"EAID_C93863FE_220D_44dc_9668_0B23BEB65A9A","Stimulus":true,"OutScope":false},{"Type":"activity","Name":"Activity2","_id":"EAID_A354F5C5_A34C_4263_AB7A_C417C3C504FF","Stimulus":false,"OutScope":false,"Group":"User"}],"OutScope":false,"PathStr":"","pathLength":0,"avgDegree":0,"archDiff":0,"boundaryNum":0,"controlNum":0,"entityNum":0,"actorNum":0,"FPAnalytics":{"Operations":{},"Functional":["FUNC_NA"],"FunctionalTag":"FUNC_NA"},"TransactionAnalytics":{"Transactional":["TRAN_NA"],"TransactionalTag":"TRAN_NA","TranLength":2,"TotalDegree":2},"utw":4},{"Nodes":[{"Type":"activity","Name":"ActivityInitial","_id":"EAID_C93863FE_220D_44dc_9668_0B23BEB65A9A","Stimulus":true,"OutScope":false},{"Type":"activity","Name":"Input Username and Password","_id":"EAID_FC7B0E7C_172B_4612_98DC_7BBA0C7C0E55","Stimulus":false,"OutScope":false,"Group":"System"},{"Type":"activity","Name":"Validate User Information","_id":"EAID_DD237FDE_EE4D_4fad_B594_47DE1792DC51","Stimulus":true,"OutScope":false}],"OutScope":false,"PathStr":"","pathLength":0,"avgDegree":0,"archDiff":0,"boundaryNum":0,"controlNum":0,"entityNum":0,"actorNum":0,"FPAnalytics":{"Operations":{},"Functional":["FUNC_NA"],"FunctionalTag":"FUNC_NA"},"TransactionAnalytics":{"Transactional":["TRAN_NA"],"TransactionalTag":"TRAN_NA","TranLength":3,"TotalDegree":3},"utw":4},{"Nodes":[{"Type":"activity","Name":"Validate User Information","_id":"EAID_DD237FDE_EE4D_4fad_B594_47DE1792DC51","Stimulus":true,"OutScope":false},{"Type":"activity","Name":"ActivityFinal","_id":"EAID_57571220_8292_4867_AD5D_2A623D1B57B7","Stimulus":false,"OutScope":false}],"OutScope":false,"PathStr":"","pathLength":0,"avgDegree":0,"archDiff":0,"boundaryNum":0,"controlNum":0,"entityNum":0,"actorNum":0,"FPAnalytics":{"Operations":{},"Functional":["FUNC_NA"],"FunctionalTag":"FUNC_NA"},"TransactionAnalytics":{"Transactional":["TRAN_NA"],"TransactionalTag":"TRAN_NA","TranLength":2,"TotalDegree":2},"utw":4},{"Nodes":[{"Type":"activity","Name":"Validate User Information","_id":"EAID_DD237FDE_EE4D_4fad_B594_47DE1792DC51","Stimulus":true,"OutScope":false},{"Type":"activity","Name":"Input Username and Password","_id":"EAID_FC7B0E7C_172B_4612_98DC_7BBA0C7C0E55","Stimulus":false,"OutScope":false,"Group":"System"},{"Type":"activity","Name":"Validate User Information","_id":"EAID_DD237FDE_EE4D_4fad_B594_47DE1792DC51","Stimulus":true,"OutScope":false}],"OutScope":false,"PathStr":"","pathLength":0,"avgDegree":0,"archDiff":0,"boundaryNum":0,"controlNum":0,"entityNum":0,"actorNum":0,"FPAnalytics":{"Operations":{},"Functional":["FUNC_NA"],"FunctionalTag":"FUNC_NA"},"TransactionAnalytics":{"Transactional":["TRAN_NA"],"TransactionalTag":"TRAN_NA","TranLength":3,"TotalDegree":3},"utw":4},{"Nodes":[{"Type":"activity","Name":"fork","_id":"EAID_1786B25E_D00D_4594_921F_04BA17E27C67","Stimulus":true,"OutScope":false},{"Type":"activity","Name":"Validate User Information","_id":"EAID_DD237FDE_EE4D_4fad_B594_47DE1792DC51","Stimulus":true,"OutScope":false}],"OutScope":false,"PathStr":"","pathLength":0,"avgDegree":0,"archDiff":0,"boundaryNum":0,"controlNum":0,"entityNum":0,"actorNum":0,"FPAnalytics":{"Operations":{},"Functional":["FUNC_NA"],"FunctionalTag":"FUNC_NA"},"TransactionAnalytics":{"Transactional":["TRAN_NA"],"TransactionalTag":"TRAN_NA","TranLength":2,"TotalDegree":2},"utw":4},{"Nodes":[{"Type":"activity","Name":"fork","_id":"EAID_1786B25E_D00D_4594_921F_04BA17E27C67","Stimulus":true,"OutScope":false},{"Type":"activity","Name":"Input Username and Password","_id":"EAID_FC7B0E7C_172B_4612_98DC_7BBA0C7C0E55","Stimulus":false,"OutScope":false,"Group":"System"},{"Type":"activity","Name":"Validate User Information","_id":"EAID_DD237FDE_EE4D_4fad_B594_47DE1792DC51","Stimulus":true,"OutScope":false}],"OutScope":false,"PathStr":"","pathLength":0,"avgDegree":0,"archDiff":0,"boundaryNum":0,"controlNum":0,"entityNum":0,"actorNum":0,"FPAnalytics":{"Operations":{},"Functional":["FUNC_NA"],"FunctionalTag":"FUNC_NA"},"TransactionAnalytics":{"Transactional":["TRAN_NA"],"TransactionalTag":"TRAN_NA","TranLength":3,"TotalDegree":3},"utw":4},{"Nodes":[{"Type":"activity","Name":"ActivityInitial","_id":"EAID_C93863FE_220D_44dc_9668_0B23BEB65A9A","Stimulus":true,"OutScope":false},{"Type":"activity","Name":"Activity2","_id":"EAID_A354F5C5_A34C_4263_AB7A_C417C3C504FF","Stimulus":false,"OutScope":false,"Group":"User"}],"OutScope":false,"PathStr":"","pathLength":0,"avgDegree":0,"archDiff":0,"boundaryNum":0,"controlNum":0,"entityNum":0,"actorNum":0,"FPAnalytics":{"Operations":{},"Functional":["FUNC_NA"],"FunctionalTag":"FUNC_NA"},"TransactionAnalytics":{"Transactional":["TRAN_NA"],"TransactionalTag":"TRAN_NA","TranLength":2,"TotalDegree":2},"utw":4},{"Nodes":[{"Type":"activity","Name":"ActivityInitial","_id":"EAID_C93863FE_220D_44dc_9668_0B23BEB65A9A","Stimulus":true,"OutScope":false},{"Type":"activity","Name":"Input Username and Password","_id":"EAID_FC7B0E7C_172B_4612_98DC_7BBA0C7C0E55","Stimulus":false,"OutScope":false,"Group":"System"},{"Type":"activity","Name":"Validate User Information","_id":"EAID_DD237FDE_EE4D_4fad_B594_47DE1792DC51","Stimulus":true,"OutScope":false}],"OutScope":false,"PathStr":"","pathLength":0,"avgDegree":0,"archDiff":0,"boundaryNum":0,"controlNum":0,"entityNum":0,"actorNum":0,"FPAnalytics":{"Operations":{},"Functional":["FUNC_NA"],"FunctionalTag":"FUNC_NA"},"TransactionAnalytics":{"Transactional":["TRAN_NA"],"TransactionalTag":"TRAN_NA","TranLength":3,"TotalDegree":3},"utw":4},{"Nodes":[{"Type":"activity","Name":"Validate User Information","_id":"EAID_DD237FDE_EE4D_4fad_B594_47DE1792DC51","Stimulus":true,"OutScope":false},{"Type":"activity","Name":"ActivityFinal","_id":"EAID_57571220_8292_4867_AD5D_2A623D1B57B7","Stimulus":false,"OutScope":false}],"OutScope":false,"PathStr":"","pathLength":0,"avgDegree":0,"archDiff":0,"boundaryNum":0,"controlNum":0,"entityNum":0,"actorNum":0,"FPAnalytics":{"Operations":{},"Functional":["FUNC_NA"],"FunctionalTag":"FUNC_NA"},"TransactionAnalytics":{"Transactional":["TRAN_NA"],"TransactionalTag":"TRAN_NA","TranLength":2,"TotalDegree":2},"utw":4},{"Nodes":[{"Type":"activity","Name":"Validate User Information","_id":"EAID_DD237FDE_EE4D_4fad_B594_47DE1792DC51","Stimulus":true,"OutScope":false},{"Type":"activity","Name":"Input Username and Password","_id":"EAID_FC7B0E7C_172B_4612_98DC_7BBA0C7C0E55","Stimulus":false,"OutScope":false,"Group":"System"},{"Type":"activity","Name":"Validate User Information","_id":"EAID_DD237FDE_EE4D_4fad_B594_47DE1792DC51","Stimulus":true,"OutScope":false}],"OutScope":false,"PathStr":"","pathLength":0,"avgDegree":0,"archDiff":0,"boundaryNum":0,"controlNum":0,"entityNum":0,"actorNum":0,"FPAnalytics":{"Operations":{},"Functional":["FUNC_NA"],"FunctionalTag":"FUNC_NA"},"TransactionAnalytics":{"Transactional":["TRAN_NA"],"TransactionalTag":"TRAN_NA","TranLength":3,"TotalDegree":3},"utw":4}]