[
  {
    "column name": "UseCase_Num",
    "statistics": {
      "mean": 8,
      "variance": "NA",
      "first_quartile": 8,
      "median": 8,
      "third_quartile": 8,
      "kurtosis": "NaN"
    },
    "dist chart path": "H:\\ResearchSpace\\ResearchProjects\\UMLx\\data\\577 Projects\\12-22\\F14a_women_at_work_website_redesign_2018-11-22@1545551707458_analysis/UseCase_Num_distribution_chart.svg"
  },
  {
    "column name": "Tran_Num",
    "statistics": {
      "mean": 61,
      "variance": "NA",
      "first_quartile": 61,
      "median": 61,
      "third_quartile": 61,
      "kurtosis": "NaN"
    },
    "dist chart path": "H:\\ResearchSpace\\ResearchProjects\\UMLx\\data\\577 Projects\\12-22\\F14a_women_at_work_website_redesign_2018-11-22@1545551707458_analysis/Tran_Num_distribution_chart.svg"
  },
  {
    "column name": "Activity_Num",
    "statistics": {
      "mean": 113,
      "variance": "NA",
      "first_quartile": 113,
      "median": 113,
      "third_quartile": 113,
      "kurtosis": "NaN"
    },
    "dist chart path": "H:\\ResearchSpace\\ResearchProjects\\UMLx\\data\\577 Projects\\12-22\\F14a_women_at_work_website_redesign_2018-11-22@1545551707458_analysis/Activity_Num_distribution_chart.svg"
  },
  {
    "column name": "Component_Num",
    "statistics": {
      "mean": 15,
      "variance": "NA",
      "first_quartile": 15,
      "median": 15,
      "third_quartile": 15,
      "kurtosis": "NaN"
    },
    "dist chart path": "H:\\ResearchSpace\\ResearchProjects\\UMLx\\data\\577 Projects\\12-22\\F14a_women_at_work_website_redesign_2018-11-22@1545551707458_analysis/Component_Num_distribution_chart.svg"
  },
  {
    "column name": "Precedence_Num",
    "statistics": {
      "mean": 102,
      "variance": "NA",
      "first_quartile": 102,
      "median": 102,
      "third_quartile": 102,
      "kurtosis": "NaN"
    },
    "dist chart path": "H:\\ResearchSpace\\ResearchProjects\\UMLx\\data\\577 Projects\\12-22\\F14a_women_at_work_website_redesign_2018-11-22@1545551707458_analysis/Precedence_Num_distribution_chart.svg"
  },
  {
    "column name": "Stimulus_Num",
    "statistics": {
      "mean": 24,
      "variance": "NA",
      "first_quartile": 24,
      "median": 24,
      "third_quartile": 24,
      "kurtosis": "NaN"
    },
    "dist chart path": "H:\\ResearchSpace\\ResearchProjects\\UMLx\\data\\577 Projects\\12-22\\F14a_women_at_work_website_redesign_2018-11-22@1545551707458_analysis/Stimulus_Num_distribution_chart.svg"
  }
] 
