{"EstimationModel":"eucp_lm","SizeMetric":"EUCP","TransactionMetric":"SWTI","Effort":"291.92","UseCases":[{"Name":"src","_id":"src","SizeMeasurement":"41.61","feasible":true,"Personnel_UI":"50.00%","Personnel_DB":"25.00%","Personnel_FS":"25.00%","Personnel":1,"Duration":"3.41","Effort":"291.92","useCasePMEffort":"-1.00","useCaseDEVEffort":"-1.00","synthesizedEffort":"291.92","BusinessValue":0,"BVEffortRatio":"0.00"}],"DomainModel":{"MVCEstimates":{"ViewEffort":"0.00","ModelEffort":"0.00","ControlEffort":"0.00"}},"SizeMeasurement":"41.61","feasible":true,"Personnel":1,"Duration":"3.41","HoursPerMonth":152,"Personnel_UI":"50.00%","Personnel_DB":"25.00%","Personnel_FS":"25.00%","TotalSynthesizedEffort":291.92,"EstimationResultsFile":"estimationResultEUCP.json"}