<?xml version="1.0" encoding="UTF-8" standalone="yes"?>
<unit xmlns="http://www.srcML.org/srcML/src" revision="0.9.5" language="Java" filename="D:\AndroidAnalysis\Instrumentation-apps\superCleanMaster\app\src\main\java\com\balaganovrocks\yourmasterclean\bean\ProcessInfo.java"><comment type="block">/*
 * Copyright (C) 2012 www.amsoft.cn
 * 
 * Licensed under the Apache License, Version 2.0 (the "License");
 * you may not use this file except in compliance with the License.
 * You may obtain a copy of the License at
 *
 *     http://www.apache.org/licenses/LICENSE-2.0
 *
 * Unless required by applicable law or agreed to in writing, software
 * distributed under the License is distributed on an "AS IS" BASIS,
 * WITHOUT WARRANTIES OR CONDITIONS OF ANY KIND, either express or implied.
 * See the License for the specific language governing permissions and
 * limitations under the License.
 */</comment>
<package>package <name><name>com</name><operator>.</operator><name>balaganovrocks</name><operator>.</operator><name>yourmasterclean</name><operator>.</operator><name>bean</name></name>;</package>



<comment type="line">// TODO: Auto-generated Javadoc</comment>
<comment type="block" format="javadoc">/**

 */</comment>
<class><specifier>public</specifier> class <name>ProcessInfo</name><block>{

	<comment type="block" format="javadoc">/**
	 * The user id of this process.
	 */</comment>
	<decl_stmt><decl><specifier>public</specifier> <type><name>String</name></type> <name>uid</name></decl>;</decl_stmt>
	
	<comment type="block" format="javadoc">/** The name of the process that this object is associated with. */</comment>
	<decl_stmt><decl><specifier>public</specifier> <type><name>String</name></type> <name>processName</name></decl>;</decl_stmt>

	<comment type="block" format="javadoc">/** The pid of this process; 0 if none. */</comment>
	<decl_stmt><decl><specifier>public</specifier> <type><name>int</name></type> <name>pid</name></decl>;</decl_stmt>

	<comment type="block" format="javadoc">/**  占用的内存 B. */</comment>
	<decl_stmt><decl><specifier>public</specifier> <type><name>long</name></type> <name>memory</name></decl>;</decl_stmt>
	
	<comment type="block" format="javadoc">/**  占用的CPU. */</comment>
	<decl_stmt><decl><specifier>public</specifier> <type><name>String</name></type> <name>cpu</name></decl>;</decl_stmt>
	
	<comment type="block" format="javadoc">/**  进程的状态，其中S表示休眠，R表示正在运行，Z表示僵死状态，N表示该进程优先值是负数. */</comment>
	<decl_stmt><decl><specifier>public</specifier> <type><name>String</name></type> <name>status</name></decl>;</decl_stmt>
	
	<comment type="block" format="javadoc">/**  当前使用的线程数. */</comment>
	<decl_stmt><decl><specifier>public</specifier> <type><name>String</name></type> <name>threadsCount</name></decl>;</decl_stmt>
	
	<comment type="block" format="javadoc">/**
	 * Instantiates a new ab process info.
	 */</comment>
	<constructor><specifier>public</specifier> <name>ProcessInfo</name><parameter_list>()</parameter_list> <block>{
		<expr_stmt><expr><call><name>super</name><argument_list>()</argument_list></call></expr>;</expr_stmt>
	}</block></constructor>

	<comment type="block" format="javadoc">/**
	 * Instantiates a new ab process info.
	 *
	 * @param processName the process name
	 * @param pid the pid
	 */</comment>
	<constructor><specifier>public</specifier> <name>ProcessInfo</name><parameter_list>(<parameter><decl><type><name>String</name></type> <name>processName</name></decl></parameter>, <parameter><decl><type><name>int</name></type> <name>pid</name></decl></parameter>)</parameter_list> <block>{
		<expr_stmt><expr><call><name>super</name><argument_list>()</argument_list></call></expr>;</expr_stmt>
		<expr_stmt><expr><name><name>this</name><operator>.</operator><name>processName</name></name> <operator>=</operator> <name>processName</name></expr>;</expr_stmt>
		<expr_stmt><expr><name><name>this</name><operator>.</operator><name>pid</name></name> <operator>=</operator> <name>pid</name></expr>;</expr_stmt>
	}</block></constructor>


}</block></class>
</unit>
