{"EstimationModel":"exucp_lm","SizeMetric":"EXUCP","TransactionMetric":"SWTII","Effort":"348.70","UseCases":[{"Name":"Add course","_id":"EAID_DA60FBE3_30C1_4edc_AE75_A75028CF6A9A","SizeMeasurement":"8.38","feasible":true,"Personnel_UI":"50.00%","Personnel_DB":"25.00%","Personnel_FS":"25.00%","Personnel":3,"Duration":"1.16","Effort":"10.87","useCasePMEffort":"-1.00","useCaseDEVEffort":"-1.00","synthesizedEffort":"10.87","BusinessValue":0,"BVEffortRatio":"0.00"},{"Name":"Delete course","_id":"EAID_AEC09FD6_3571_43c5_9D9A_016420081A61","SizeMeasurement":"23.22","feasible":true,"Personnel_UI":"50.00%","Personnel_DB":"25.00%","Personnel_FS":"25.00%","Personnel":3,"Duration":"1.62","Effort":"30.10","useCasePMEffort":"-1.00","useCaseDEVEffort":"-1.00","synthesizedEffort":"30.10","BusinessValue":0,"BVEffortRatio":"0.00"},{"Name":"Login","_id":"EAID_D72AE362_52CB_4b7a_A51E_196760DE87E8","SizeMeasurement":"16.43","feasible":true,"Personnel_UI":"40.00%","Personnel_DB":"40.00%","Personnel_FS":"20.00%","Personnel":3,"Duration":"1.44","Effort":"21.30","useCasePMEffort":"-1.00","useCaseDEVEffort":"-1.00","synthesizedEffort":"21.30","BusinessValue":0,"BVEffortRatio":"0.00"},{"Name":"Logout","_id":"EAID_367D3E3F_EB56_401a_9D74_9274FAB9584B","SizeMeasurement":"0.00","feasible":true,"Personnel_UI":"50.00%","Personnel_DB":"25.00%","Personnel_FS":"25.00%","Personnel":3,"Duration":"0.00","Effort":"0.00","useCasePMEffort":"-1.00","useCaseDEVEffort":"-1.00","synthesizedEffort":"0.00","BusinessValue":0,"BVEffortRatio":"0.00"},{"Name":"Modify course","_id":"EAID_D451FE2C_D855_4acf_946C_0F234BA1E279","SizeMeasurement":"29.42","feasible":true,"Personnel_UI":"40.00%","Personnel_DB":"20.00%","Personnel_FS":"40.00%","Personnel":3,"Duration":"1.75","Effort":"38.13","useCasePMEffort":"-1.00","useCaseDEVEffort":"-1.00","synthesizedEffort":"38.13","BusinessValue":0,"BVEffortRatio":"0.00"},{"Name":"Register course","_id":"EAID_CEB11843_18FC_4831_82DC_B9EACF4F50DE","SizeMeasurement":"20.54","feasible":true,"Personnel_UI":"60.00%","Personnel_DB":"20.00%","Personnel_FS":"20.00%","Personnel":3,"Duration":"1.55","Effort":"26.63","useCasePMEffort":"-1.00","useCaseDEVEffort":"-1.00","synthesizedEffort":"26.63","BusinessValue":0,"BVEffortRatio":"0.00"},{"Name":"Request new course","_id":"EAID_569C445F_D34D_48b8_A740_BAEC25117D0A","SizeMeasurement":"9.62","feasible":true,"Personnel_UI":"60.00%","Personnel_DB":"20.00%","Personnel_FS":"20.00%","Personnel":3,"Duration":"1.21","Effort":"12.48","useCasePMEffort":"-1.00","useCaseDEVEffort":"-1.00","synthesizedEffort":"12.48","BusinessValue":0,"BVEffortRatio":"0.00"},{"Name":"Review course","_id":"EAID_9D3D4DC4_4556_4cf6_94F4_3C90F31837E2","SizeMeasurement":"54.80","feasible":true,"Personnel_UI":"60.00%","Personnel_DB":"20.00%","Personnel_FS":"20.00%","Personnel":3,"Duration":"2.14","Effort":"71.04","useCasePMEffort":"-1.00","useCaseDEVEffort":"-1.00","synthesizedEffort":"71.04","BusinessValue":0,"BVEffortRatio":"0.00"},{"Name":"Search course","_id":"EAID_495ADE75_ED32_44d3_9E96_5C4BAB23C2A0","SizeMeasurement":"16.32","feasible":true,"Personnel_UI":"60.00%","Personnel_DB":"20.00%","Personnel_FS":"20.00%","Personnel":3,"Duration":"1.44","Effort":"21.16","useCasePMEffort":"-1.00","useCaseDEVEffort":"-1.00","synthesizedEffort":"21.16","BusinessValue":0,"BVEffortRatio":"0.00"},{"Name":"Setup account","_id":"EAID_C3562026_2AFF_4ec9_92BC_3D043FDB04F3","SizeMeasurement":"6.61","feasible":true,"Personnel_UI":"50.00%","Personnel_DB":"25.00%","Personnel_FS":"25.00%","Personnel":3,"Duration":"1.07","Effort":"8.57","useCasePMEffort":"-1.00","useCaseDEVEffort":"-1.00","synthesizedEffort":"8.57","BusinessValue":0,"BVEffortRatio":"0.00"},{"Name":"Share course","_id":"EAID_24330CF3_C571_454e_BFA3_782A413727F3","SizeMeasurement":"29.56","feasible":true,"Personnel_UI":"60.00%","Personnel_DB":"20.00%","Personnel_FS":"20.00%","Personnel":3,"Duration":"1.75","Effort":"38.32","useCasePMEffort":"-1.00","useCaseDEVEffort":"-1.00","synthesizedEffort":"38.32","BusinessValue":0,"BVEffortRatio":"0.00"},{"Name":"Update schedule","_id":"EAID_F332DE19_12D9_443c_963E_A1DDD82EA33C","SizeMeasurement":"25.39","feasible":true,"Personnel_UI":"50.00%","Personnel_DB":"25.00%","Personnel_FS":"25.00%","Personnel":3,"Duration":"1.67","Effort":"32.92","useCasePMEffort":"-1.00","useCaseDEVEffort":"-1.00","synthesizedEffort":"32.92","BusinessValue":0,"BVEffortRatio":"0.00"},{"Name":"Verify new course","_id":"EAID_3011838C_B2EB_4a8a_8202_39F02846E1F6","SizeMeasurement":"28.68","feasible":true,"Personnel_UI":"20.00%","Personnel_DB":"20.00%","Personnel_FS":"60.00%","Personnel":3,"Duration":"1.73","Effort":"37.18","useCasePMEffort":"-1.00","useCaseDEVEffort":"-1.00","synthesizedEffort":"37.18","BusinessValue":0,"BVEffortRatio":"0.00"}],"DomainModel":{"MVCEstimates":{"ViewEffort":"130.76","ModelEffort":"43.59","ControlEffort":"174.35"}},"SizeMeasurement":"269.98","feasible":true,"Personnel":1,"Duration":"3.61","HoursPerMonth":152,"Personnel_UI":"50.00%","Personnel_DB":"23.46%","Personnel_FS":"26.54%","TotalSynthesizedEffort":348.70000000000005,"EstimationResultsFile":"estimationResultEXUCP.json"}