{"EstimationModel":"eucp_lm","SizeMetric":"EUCP","TransactionMetric":"SWTI","Effort":"711.89","UseCases":[{"Name":"Add course","_id":"EAID_DA60FBE3_30C1_4edc_AE75_A75028CF6A9A","SizeMeasurement":"5.07","feasible":true,"Personnel_UI":"50.00%","Personnel_DB":"25.00%","Personnel_FS":"25.00%","Personnel":3,"Duration":"1.72","Effort":"35.95","useCasePMEffort":"-1.00","useCaseDEVEffort":"-1.00","synthesizedEffort":"35.95","BusinessValue":0,"BVEffortRatio":"0.00"},{"Name":"Delete course","_id":"EAID_AEC09FD6_3571_43c5_9D9A_016420081A61","SizeMeasurement":"7.10","feasible":true,"Personnel_UI":"50.00%","Personnel_DB":"25.00%","Personnel_FS":"25.00%","Personnel":3,"Duration":"1.92","Effort":"50.34","useCasePMEffort":"-1.00","useCaseDEVEffort":"-1.00","synthesizedEffort":"50.34","BusinessValue":0,"BVEffortRatio":"0.00"},{"Name":"Login","_id":"EAID_D72AE362_52CB_4b7a_A51E_196760DE87E8","SizeMeasurement":"9.13","feasible":true,"Personnel_UI":"40.00%","Personnel_DB":"40.00%","Personnel_FS":"20.00%","Personnel":3,"Duration":"2.08","Effort":"64.72","useCasePMEffort":"-1.00","useCaseDEVEffort":"-1.00","synthesizedEffort":"64.72","BusinessValue":0,"BVEffortRatio":"0.00"},{"Name":"Logout","_id":"EAID_367D3E3F_EB56_401a_9D74_9274FAB9584B","SizeMeasurement":"0.00","feasible":true,"Personnel_UI":"50.00%","Personnel_DB":"25.00%","Personnel_FS":"25.00%","Personnel":3,"Duration":"0.00","Effort":"0.00","useCasePMEffort":"-1.00","useCaseDEVEffort":"-1.00","synthesizedEffort":"0.00","BusinessValue":0,"BVEffortRatio":"0.00"},{"Name":"Modify course","_id":"EAID_D451FE2C_D855_4acf_946C_0F234BA1E279","SizeMeasurement":"10.15","feasible":true,"Personnel_UI":"40.00%","Personnel_DB":"20.00%","Personnel_FS":"40.00%","Personnel":3,"Duration":"2.15","Effort":"71.91","useCasePMEffort":"-1.00","useCaseDEVEffort":"-1.00","synthesizedEffort":"71.91","BusinessValue":0,"BVEffortRatio":"0.00"},{"Name":"Register course","_id":"EAID_CEB11843_18FC_4831_82DC_B9EACF4F50DE","SizeMeasurement":"9.13","feasible":true,"Personnel_UI":"60.00%","Personnel_DB":"20.00%","Personnel_FS":"20.00%","Personnel":3,"Duration":"2.08","Effort":"64.72","useCasePMEffort":"-1.00","useCaseDEVEffort":"-1.00","synthesizedEffort":"64.72","BusinessValue":0,"BVEffortRatio":"0.00"},{"Name":"Request new course","_id":"EAID_569C445F_D34D_48b8_A740_BAEC25117D0A","SizeMeasurement":"6.09","feasible":true,"Personnel_UI":"60.00%","Personnel_DB":"20.00%","Personnel_FS":"20.00%","Personnel":3,"Duration":"1.82","Effort":"43.14","useCasePMEffort":"-1.00","useCaseDEVEffort":"-1.00","synthesizedEffort":"43.14","BusinessValue":0,"BVEffortRatio":"0.00"},{"Name":"Review course","_id":"EAID_9D3D4DC4_4556_4cf6_94F4_3C90F31837E2","SizeMeasurement":"14.21","feasible":true,"Personnel_UI":"60.00%","Personnel_DB":"20.00%","Personnel_FS":"20.00%","Personnel":3,"Duration":"2.40","Effort":"100.67","useCasePMEffort":"-1.00","useCaseDEVEffort":"-1.00","synthesizedEffort":"100.67","BusinessValue":0,"BVEffortRatio":"0.00"},{"Name":"Search course","_id":"EAID_495ADE75_ED32_44d3_9E96_5C4BAB23C2A0","SizeMeasurement":"9.13","feasible":true,"Personnel_UI":"60.00%","Personnel_DB":"20.00%","Personnel_FS":"20.00%","Personnel":3,"Duration":"2.08","Effort":"64.72","useCasePMEffort":"-1.00","useCaseDEVEffort":"-1.00","synthesizedEffort":"64.72","BusinessValue":0,"BVEffortRatio":"0.00"},{"Name":"Setup account","_id":"EAID_C3562026_2AFF_4ec9_92BC_3D043FDB04F3","SizeMeasurement":"5.07","feasible":true,"Personnel_UI":"50.00%","Personnel_DB":"25.00%","Personnel_FS":"25.00%","Personnel":3,"Duration":"1.72","Effort":"35.95","useCasePMEffort":"-1.00","useCaseDEVEffort":"-1.00","synthesizedEffort":"35.95","BusinessValue":0,"BVEffortRatio":"0.00"},{"Name":"Share course","_id":"EAID_24330CF3_C571_454e_BFA3_782A413727F3","SizeMeasurement":"8.12","feasible":true,"Personnel_UI":"60.00%","Personnel_DB":"20.00%","Personnel_FS":"20.00%","Personnel":3,"Duration":"2.00","Effort":"57.53","useCasePMEffort":"-1.00","useCaseDEVEffort":"-1.00","synthesizedEffort":"57.53","BusinessValue":0,"BVEffortRatio":"0.00"},{"Name":"Update schedule","_id":"EAID_F332DE19_12D9_443c_963E_A1DDD82EA33C","SizeMeasurement":"8.12","feasible":true,"Personnel_UI":"50.00%","Personnel_DB":"25.00%","Personnel_FS":"25.00%","Personnel":3,"Duration":"2.00","Effort":"57.53","useCasePMEffort":"-1.00","useCaseDEVEffort":"-1.00","synthesizedEffort":"57.53","BusinessValue":0,"BVEffortRatio":"0.00"},{"Name":"Verify new course","_id":"EAID_3011838C_B2EB_4a8a_8202_39F02846E1F6","SizeMeasurement":"9.13","feasible":true,"Personnel_UI":"20.00%","Personnel_DB":"20.00%","Personnel_FS":"60.00%","Personnel":3,"Duration":"2.08","Effort":"64.72","useCasePMEffort":"-1.00","useCaseDEVEffort":"-1.00","synthesizedEffort":"64.72","BusinessValue":0,"BVEffortRatio":"0.00"}],"DomainModel":{"MVCEstimates":{"ViewEffort":"266.96","ModelEffort":"88.99","ControlEffort":"355.94"}},"SizeMeasurement":"101.47","feasible":true,"Personnel":2,"Duration":"4.57","HoursPerMonth":152,"Personnel_UI":"50.00%","Personnel_DB":"23.46%","Personnel_FS":"26.54%","TotalSynthesizedEffort":711.9,"EstimationResultsFile":"estimationResultEUCP.json"}