<?xml version="1.0" encoding="windows-1252"?>
<xmi:XMI xmi:version="2.1" xmlns:uml="http://schema.omg.org/spec/UML/2.1" xmlns:xmi="http://schema.omg.org/spec/XMI/2.1">
	<xmi:Documentation exporter="Enterprise Architect" exporterVersion="6.5"/>
	<uml:Model xmi:type="uml:Model" name="EA_Model" visibility="public">
		<packagedElement xmi:type="uml:Package" xmi:id="EAPK_B6531671_DAD8_4725_8168_0ED3FF59FCFD" name="Model" visibility="public">
			<packagedElement xmi:type="uml:Package" xmi:id="EAPK_0595F4BC_E9EB_43e9_9C60_143B5E25C705" name="SSAD_IOC3_S13b_T09_V3.2" visibility="public">
				<packagedElement xmi:type="uml:Class" xmi:id="EAID_068ADAEC_3A78_4087_9E42_FCB4E979D673" name="Base_module_model" visibility="public">
					<ownedAttribute xmi:type="uml:Property" xmi:id="EAID_C3121CF1_5ED5_43cc_AE51_559D94A178DF" name="db" visibility="private" isStatic="false" isReadOnly="false" isDerived="false" isOrdered="false" isUnique="true" isDerivedUnion="false">
						<lowerValue xmi:type="uml:LiteralInteger" xmi:id="EAID_LI000001_5ED5_43cc_AE51_559D94A178DF" value="1"/>
						<upperValue xmi:type="uml:LiteralInteger" xmi:id="EAID_LI000002_5ED5_43cc_AE51_559D94A178DF" value="1"/>
						<type xmi:idref="EAJava_Db_active_rec"/>
					</ownedAttribute>
					<ownedOperation xmi:id="EAID_203AB910_30B9_4133_824B_42961695809A" name="_construct" visibility="public" concurrency="sequential">
						<ownedParameter xmi:id="EAID_RT000000_30B9_4133_824B_42961695809A" name="return" direction="return" type="EAJava_void"/>
					</ownedOperation>
					<ownedOperation xmi:id="EAID_BA8608AB_47AE_463e_A4FA_6D6399F21887" name="list_items" visibility="public" concurrency="sequential">
						<ownedParameter xmi:id="EAID_RT000000_47AE_463e_A4FA_6D6399F21887" name="return" direction="return" type="EAJava_void"/>
					</ownedOperation>
					<ownedOperation xmi:id="EAID_18961933_150C_4b61_BCFD_7AE23AC30223" name="form_fields" visibility="public" concurrency="sequential">
						<ownedParameter xmi:id="EAID_FDB64505_B122_43b4_BC80_FCA331238E86" name="values" direction="in" isStream="false" isException="false" isOrdered="false" isUnique="true" type="EAJava_Array"/>
						<ownedParameter xmi:id="EAID_RT000000_150C_4b61_BCFD_7AE23AC30223" name="return" direction="return" type="EAJava_void"/>
					</ownedOperation>
					<ownedOperation xmi:id="EAID_EE7D97BF_D46F_4f23_9F26_790A1B85671C" name="on_before_validate" visibility="public" concurrency="sequential">
						<ownedParameter xmi:id="EAID_C1A17153_B793_4a2c_9BD3_505FD1136C65" name="values" direction="in" isStream="false" isException="false" isOrdered="false" isUnique="true" type="EAJava_Array"/>
						<ownedParameter xmi:id="EAID_RT000000_D46F_4f23_9F26_790A1B85671C" name="return" direction="return" type="EAJava_void"/>
					</ownedOperation>
					<ownedOperation xmi:id="EAID_E0880BA0_AD57_44e6_8F8C_7A910AFC629B" name="on_after_post" visibility="public" concurrency="sequential">
						<ownedParameter xmi:id="EAID_5CBF5E9A_9F4F_457c_A2D0_E9BD686BAEB8" name="values" direction="in" isStream="false" isException="false" isOrdered="false" isUnique="true" type="EAJava_Array"/>
						<ownedParameter xmi:id="EAID_RT000000_AD57_44e6_8F8C_7A910AFC629B" name="return" direction="return" type="EAJava_void"/>
					</ownedOperation>
				</packagedElement>
				<packagedElement xmi:type="uml:Class" xmi:id="EAID_54F7932F_45C9_4ede_90D6_BF7466C1253D" name="Udm_library_model" visibility="public">
					<generalization xmi:type="uml:Generalization" xmi:id="EAID_793022EB_77B9_4213_A438_6A06C0D9B3BC" general="EAID_068ADAEC_3A78_4087_9E42_FCB4E979D673"/>
				</packagedElement>
				<packagedElement xmi:type="uml:Class" xmi:id="EAID_B4CF4987_0466_4db7_B945_20CEE3E6CAA1" name="Udm_microsites_model" visibility="public">
					<ownedOperation xmi:id="EAID_CC4F8E9F_2925_4353_ABF3_114241885798" name="email_microsite_link" visibility="public" concurrency="sequential">
						<ownedParameter xmi:id="EAID_RT000000_2925_4353_ABF3_114241885798" name="return" direction="return" type="EAJava_void"/>
					</ownedOperation>
					<generalization xmi:type="uml:Generalization" xmi:id="EAID_955DC0D8_98C4_4c2f_8B31_6BE9FFDB6F84" general="EAID_068ADAEC_3A78_4087_9E42_FCB4E979D673"/>
				</packagedElement>
				<packagedElement xmi:type="uml:Class" xmi:id="EAID_A87C57B9_2DC3_4660_9705_CD3AFB8F7944" name="Udm_statistics_model" visibility="public">
					<generalization xmi:type="uml:Generalization" xmi:id="EAID_375AE998_D0DD_41a0_88C7_F7C043F48B30" general="EAID_068ADAEC_3A78_4087_9E42_FCB4E979D673"/>
				</packagedElement>
				<packagedElement xmi:type="uml:Class" xmi:id="EAID_BD878BBE_4E5D_4d79_B379_E0EA41428A58" name="Udm_subsciption" visibility="public">
					<generalization xmi:type="uml:Generalization" xmi:id="EAID_9AAFA639_A353_4859_9E80_1C3470211ACE" general="EAID_068ADAEC_3A78_4087_9E42_FCB4E979D673"/>
				</packagedElement>
			</packagedElement>
		</packagedElement>
	</uml:Model>
	<xmi:Extension extender="Enterprise Architect" extenderID="6.5">
		<elements>
			<element xmi:idref="EAPK_B6531671_DAD8_4725_8168_0ED3FF59FCFD">
				<packageproperties/>
				<paths/>
				<times created="2012-04-17 00:00:00" modified="2012-04-17 00:00:00"/>
				<flags iscontrolled="FALSE" isprotected="FALSE" usedtd="FALSE" logxml="FALSE" packageFlags="isModel=1;"/>
			</element>
			<element xmi:idref="EAPK_0595F4BC_E9EB_43e9_9C60_143B5E25C705" xmi:type="uml:Package" name="SSAD_IOC3_S13b_T09_V3.2" scope="public">
				<model package2="EAID_0595F4BC_E9EB_43e9_9C60_143B5E25C705" package="EAPK_B6531671_DAD8_4725_8168_0ED3FF59FCFD" tpos="0" ea_localid="2" ea_eleType="package"/>
				<properties isSpecification="false" sType="Package" nType="0" scope="public"/>
				<project author="SatyaAnanya" version="1.0" phase="1.0" created="2017-10-15 10:39:07" modified="2017-10-15 10:39:07" complexity="1" status="Proposed"/>
				<code gentype="Java"/>
				<style appearance="BackColor=-1;BorderColor=-1;BorderWidth=-1;FontColor=-1;VSwimLanes=1;HSwimLanes=1;BorderStyle=0;"/>
				<tags/>
				<xrefs/>
				<extendedProperties tagged="0" package_name="Model"/>
				<packageproperties version="1.0"/>
				<paths/>
				<times created="2017-10-15 10:39:07" modified="2017-10-15 10:39:07"/>
				<flags iscontrolled="FALSE" isprotected="FALSE" usedtd="FALSE" logxml="FALSE" packageFlags="isModel=1;VICON=3;"/>
			</element>
			<element xmi:idref="EAID_068ADAEC_3A78_4087_9E42_FCB4E979D673" xmi:type="uml:Class" name="Base_module_model" scope="public">
				<model package="EAPK_0595F4BC_E9EB_43e9_9C60_143B5E25C705" tpos="0" ea_localid="2" ea_eleType="element"/>
				<properties isSpecification="false" sType="Class" nType="0" scope="public" isRoot="false" isLeaf="false" isAbstract="false" isActive="false"/>
				<project author="SatyaAnanya" version="1.0" phase="1.0" created="2017-10-15 10:41:10" modified="2017-10-15 10:41:25" complexity="1" status="Proposed"/>
				<code product_name="Java" gentype="Java"/>
				<style appearance="BackColor=-1;BorderColor=-1;BorderWidth=-1;FontColor=-1;VSwimLanes=1;HSwimLanes=1;BorderStyle=0;"/>
				<tags/>
				<xrefs/>
				<extendedProperties tagged="0" package_name="SSAD_IOC3_S13b_T09_V3.2"/>
				<attributes>
					<attribute xmi:idref="EAID_C3121CF1_5ED5_43cc_AE51_559D94A178DF" name="db" scope="Private">
						<initial/>
						<documentation/>
						<model ea_localid="1" ea_guid="{C3121CF1-5ED5-43cc-AE51-559D94A178DF}"/>
						<properties type="Db_active_rec" collection="false" duplicates="0" changeability="changeable"/>
						<coords ordered="0"/>
						<containment containment="Not Specified" position="0"/>
						<stereotype/>
						<bounds lower="1" upper="1"/>
						<options/>
						<style/>
						<styleex value="volatile=0;"/>
						<tags/>
						<xrefs/>
					</attribute>
				</attributes>
				<operations>
					<operation xmi:idref="EAID_203AB910_30B9_4133_824B_42961695809A" name="_construct" scope="Public">
						<properties position="0"/>
						<stereotype/>
						<model ea_guid="{203AB910-30B9-4133-824B-42961695809A}" ea_localid="1"/>
						<type type="void" const="false" static="false" isAbstract="false" synchronised="0" concurrency="Sequential" pure="0" isQuery="false"/>
						<behaviour/>
						<code/>
						<style/>
						<styleex/>
						<documentation/>
						<tags/>
						<parameters>
							<parameter xmi:idref="EAID_RETURNID_30B9_4133_824B_42961695809A" visibility="public">
								<properties pos="0" type="void" const="false" ea_guid="{RETURNID-30B9-4133-824B-42961695809A}"/>
								<style/>
								<styleex/>
								<documentation/>
								<tags/>
								<xrefs/>
							</parameter>
						</parameters>
						<xrefs/>
					</operation>
					<operation xmi:idref="EAID_BA8608AB_47AE_463e_A4FA_6D6399F21887" name="list_items" scope="Public">
						<properties position="1"/>
						<stereotype/>
						<model ea_guid="{BA8608AB-47AE-463e-A4FA-6D6399F21887}" ea_localid="2"/>
						<type type="void" const="false" static="false" isAbstract="false" synchronised="0" concurrency="Sequential" pure="0" isQuery="false"/>
						<behaviour/>
						<code/>
						<style/>
						<styleex/>
						<documentation/>
						<tags/>
						<parameters>
							<parameter xmi:idref="EAID_RETURNID_47AE_463e_A4FA_6D6399F21887" visibility="public">
								<properties pos="0" type="void" const="false" ea_guid="{RETURNID-47AE-463e-A4FA-6D6399F21887}"/>
								<style/>
								<styleex/>
								<documentation/>
								<tags/>
								<xrefs/>
							</parameter>
						</parameters>
						<xrefs/>
					</operation>
					<operation xmi:idref="EAID_18961933_150C_4b61_BCFD_7AE23AC30223" name="form_fields" scope="Public">
						<properties position="2"/>
						<stereotype/>
						<model ea_guid="{18961933-150C-4b61-BCFD-7AE23AC30223}" ea_localid="3"/>
						<type type="void" const="false" static="false" isAbstract="false" synchronised="0" concurrency="Sequential" pure="0" isQuery="false"/>
						<behaviour/>
						<code/>
						<style/>
						<styleex/>
						<documentation/>
						<tags/>
						<parameters>
							<parameter xmi:idref="EAID_RETURNID_150C_4b61_BCFD_7AE23AC30223" visibility="public">
								<properties pos="0" type="void" const="false" ea_guid="{RETURNID-150C-4b61-BCFD-7AE23AC30223}"/>
								<style/>
								<styleex/>
								<documentation/>
								<tags/>
								<xrefs/>
							</parameter>
							<parameter xmi:idref="EAID_FDB64505_B122_43b4_BC80_FCA331238E86" visibility="public">
								<properties pos="0" type="Array" const="false" ea_guid="{FDB64505-B122-43b4-BC80-FCA331238E86}"/>
								<style/>
								<styleex/>
								<documentation/>
								<tags/>
								<xrefs/>
							</parameter>
						</parameters>
						<xrefs/>
					</operation>
					<operation xmi:idref="EAID_EE7D97BF_D46F_4f23_9F26_790A1B85671C" name="on_before_validate" scope="Public">
						<properties position="3"/>
						<stereotype/>
						<model ea_guid="{EE7D97BF-D46F-4f23-9F26-790A1B85671C}" ea_localid="4"/>
						<type type="void" const="false" static="false" isAbstract="false" synchronised="0" concurrency="Sequential" pure="0" isQuery="false"/>
						<behaviour/>
						<code/>
						<style/>
						<styleex/>
						<documentation/>
						<tags/>
						<parameters>
							<parameter xmi:idref="EAID_RETURNID_D46F_4f23_9F26_790A1B85671C" visibility="public">
								<properties pos="0" type="void" const="false" ea_guid="{RETURNID-D46F-4f23-9F26-790A1B85671C}"/>
								<style/>
								<styleex/>
								<documentation/>
								<tags/>
								<xrefs/>
							</parameter>
							<parameter xmi:idref="EAID_C1A17153_B793_4a2c_9BD3_505FD1136C65" visibility="public">
								<properties pos="0" type="Array" const="false" ea_guid="{C1A17153-B793-4a2c-9BD3-505FD1136C65}"/>
								<style/>
								<styleex/>
								<documentation/>
								<tags/>
								<xrefs/>
							</parameter>
						</parameters>
						<xrefs/>
					</operation>
					<operation xmi:idref="EAID_E0880BA0_AD57_44e6_8F8C_7A910AFC629B" name="on_after_post" scope="Public">
						<properties position="4"/>
						<stereotype/>
						<model ea_guid="{E0880BA0-AD57-44e6-8F8C-7A910AFC629B}" ea_localid="5"/>
						<type type="void" const="false" static="false" isAbstract="false" synchronised="0" concurrency="Sequential" pure="0" isQuery="false"/>
						<behaviour/>
						<code/>
						<style/>
						<styleex/>
						<documentation/>
						<tags/>
						<parameters>
							<parameter xmi:idref="EAID_RETURNID_AD57_44e6_8F8C_7A910AFC629B" visibility="public">
								<properties pos="0" type="void" const="false" ea_guid="{RETURNID-AD57-44e6-8F8C-7A910AFC629B}"/>
								<style/>
								<styleex/>
								<documentation/>
								<tags/>
								<xrefs/>
							</parameter>
							<parameter xmi:idref="EAID_5CBF5E9A_9F4F_457c_A2D0_E9BD686BAEB8" visibility="public">
								<properties pos="0" type="Array" const="false" ea_guid="{5CBF5E9A-9F4F-457c-A2D0-E9BD686BAEB8}"/>
								<style/>
								<styleex/>
								<documentation/>
								<tags/>
								<xrefs/>
							</parameter>
						</parameters>
						<xrefs/>
					</operation>
				</operations>
				<links>
					<Generalization xmi:id="EAID_375AE998_D0DD_41a0_88C7_F7C043F48B30" start="EAID_A87C57B9_2DC3_4660_9705_CD3AFB8F7944" end="EAID_068ADAEC_3A78_4087_9E42_FCB4E979D673"/>
					<Generalization xmi:id="EAID_793022EB_77B9_4213_A438_6A06C0D9B3BC" start="EAID_54F7932F_45C9_4ede_90D6_BF7466C1253D" end="EAID_068ADAEC_3A78_4087_9E42_FCB4E979D673"/>
					<Generalization xmi:id="EAID_955DC0D8_98C4_4c2f_8B31_6BE9FFDB6F84" start="EAID_B4CF4987_0466_4db7_B945_20CEE3E6CAA1" end="EAID_068ADAEC_3A78_4087_9E42_FCB4E979D673"/>
					<Generalization xmi:id="EAID_9AAFA639_A353_4859_9E80_1C3470211ACE" start="EAID_BD878BBE_4E5D_4d79_B379_E0EA41428A58" end="EAID_068ADAEC_3A78_4087_9E42_FCB4E979D673"/>
				</links>
			</element>
			<element xmi:idref="EAID_54F7932F_45C9_4ede_90D6_BF7466C1253D" xmi:type="uml:Class" name="Udm_library_model" scope="public">
				<model package="EAPK_0595F4BC_E9EB_43e9_9C60_143B5E25C705" tpos="0" ea_localid="5" ea_eleType="element"/>
				<properties isSpecification="false" sType="Class" nType="0" scope="public" isRoot="false" isLeaf="false" isAbstract="false" isActive="false"/>
				<project author="SatyaAnanya" version="1.0" phase="1.0" created="2017-10-15 10:44:46" modified="2017-10-15 10:45:03" complexity="1" status="Proposed"/>
				<code product_name="Java" gentype="Java"/>
				<style appearance="BackColor=-1;BorderColor=-1;BorderWidth=-1;FontColor=-1;VSwimLanes=1;HSwimLanes=1;BorderStyle=0;"/>
				<tags/>
				<xrefs/>
				<extendedProperties tagged="0" package_name="SSAD_IOC3_S13b_T09_V3.2"/>
				<links>
					<Generalization xmi:id="EAID_793022EB_77B9_4213_A438_6A06C0D9B3BC" start="EAID_54F7932F_45C9_4ede_90D6_BF7466C1253D" end="EAID_068ADAEC_3A78_4087_9E42_FCB4E979D673"/>
				</links>
			</element>
			<element xmi:idref="EAID_B4CF4987_0466_4db7_B945_20CEE3E6CAA1" xmi:type="uml:Class" name="Udm_microsites_model" scope="public">
				<model package="EAPK_0595F4BC_E9EB_43e9_9C60_143B5E25C705" tpos="0" ea_localid="4" ea_eleType="element"/>
				<properties isSpecification="false" sType="Class" nType="0" scope="public" isRoot="false" isLeaf="false" isAbstract="false" isActive="false"/>
				<project author="SatyaAnanya" version="1.0" phase="1.0" created="2017-10-15 10:43:56" modified="2017-10-15 10:44:12" complexity="1" status="Proposed"/>
				<code product_name="Java" gentype="Java"/>
				<style appearance="BackColor=-1;BorderColor=-1;BorderWidth=-1;FontColor=-1;VSwimLanes=1;HSwimLanes=1;BorderStyle=0;"/>
				<tags/>
				<xrefs/>
				<extendedProperties tagged="0" package_name="SSAD_IOC3_S13b_T09_V3.2"/>
				<operations>
					<operation xmi:idref="EAID_CC4F8E9F_2925_4353_ABF3_114241885798" name="email_microsite_link" scope="Public">
						<properties position="0"/>
						<stereotype/>
						<model ea_guid="{CC4F8E9F-2925-4353-ABF3-114241885798}" ea_localid="6"/>
						<type type="void" const="false" static="false" isAbstract="false" synchronised="0" concurrency="Sequential" pure="0" isQuery="false"/>
						<behaviour/>
						<code/>
						<style/>
						<styleex/>
						<documentation/>
						<tags/>
						<parameters>
							<parameter xmi:idref="EAID_RETURNID_2925_4353_ABF3_114241885798" visibility="public">
								<properties pos="0" type="void" const="false" ea_guid="{RETURNID-2925-4353-ABF3-114241885798}"/>
								<style/>
								<styleex/>
								<documentation/>
								<tags/>
								<xrefs/>
							</parameter>
						</parameters>
						<xrefs/>
					</operation>
				</operations>
				<links>
					<Generalization xmi:id="EAID_955DC0D8_98C4_4c2f_8B31_6BE9FFDB6F84" start="EAID_B4CF4987_0466_4db7_B945_20CEE3E6CAA1" end="EAID_068ADAEC_3A78_4087_9E42_FCB4E979D673"/>
				</links>
			</element>
			<element xmi:idref="EAID_A87C57B9_2DC3_4660_9705_CD3AFB8F7944" xmi:type="uml:Class" name="Udm_statistics_model" scope="public">
				<model package="EAPK_0595F4BC_E9EB_43e9_9C60_143B5E25C705" tpos="0" ea_localid="6" ea_eleType="element"/>
				<properties isSpecification="false" sType="Class" nType="0" scope="public" isRoot="false" isLeaf="false" isAbstract="false" isActive="false"/>
				<project author="SatyaAnanya" version="1.0" phase="1.0" created="2017-10-15 10:45:10" modified="2017-10-15 10:45:29" complexity="1" status="Proposed"/>
				<code product_name="Java" gentype="Java"/>
				<style appearance="BackColor=-1;BorderColor=-1;BorderWidth=-1;FontColor=-1;VSwimLanes=1;HSwimLanes=1;BorderStyle=0;"/>
				<tags/>
				<xrefs/>
				<extendedProperties tagged="0" package_name="SSAD_IOC3_S13b_T09_V3.2"/>
				<links>
					<Generalization xmi:id="EAID_375AE998_D0DD_41a0_88C7_F7C043F48B30" start="EAID_A87C57B9_2DC3_4660_9705_CD3AFB8F7944" end="EAID_068ADAEC_3A78_4087_9E42_FCB4E979D673"/>
				</links>
			</element>
			<element xmi:idref="EAID_BD878BBE_4E5D_4d79_B379_E0EA41428A58" xmi:type="uml:Class" name="Udm_subsciption" scope="public">
				<model package="EAPK_0595F4BC_E9EB_43e9_9C60_143B5E25C705" tpos="0" ea_localid="3" ea_eleType="element"/>
				<properties isSpecification="false" sType="Class" nType="0" scope="public" isRoot="false" isLeaf="false" isAbstract="false" isActive="false"/>
				<project author="SatyaAnanya" version="1.0" phase="1.0" created="2017-10-15 10:43:29" modified="2017-10-15 10:43:44" complexity="1" status="Proposed"/>
				<code product_name="Java" gentype="Java"/>
				<style appearance="BackColor=-1;BorderColor=-1;BorderWidth=-1;FontColor=-1;VSwimLanes=1;HSwimLanes=1;BorderStyle=0;"/>
				<tags/>
				<xrefs/>
				<extendedProperties tagged="0" package_name="SSAD_IOC3_S13b_T09_V3.2"/>
				<links>
					<Generalization xmi:id="EAID_9AAFA639_A353_4859_9E80_1C3470211ACE" start="EAID_BD878BBE_4E5D_4d79_B379_E0EA41428A58" end="EAID_068ADAEC_3A78_4087_9E42_FCB4E979D673"/>
				</links>
			</element>
		</elements>
		<connectors>
			<connector xmi:idref="EAID_375AE998_D0DD_41a0_88C7_F7C043F48B30">
				<source xmi:idref="EAID_A87C57B9_2DC3_4660_9705_CD3AFB8F7944">
					<model ea_localid="6" type="Class" name="Udm_statistics_model"/>
					<role visibility="Public" targetScope="instance"/>
					<type aggregation="none" containment="Unspecified"/>
					<constraints/>
					<modifiers isOrdered="false" changeable="none" isNavigable="false"/>
					<style value="Union=0;Derived=0;AllowDuplicates=0;"/>
					<documentation/>
					<xrefs/>
					<tags/>
				</source>
				<target xmi:idref="EAID_068ADAEC_3A78_4087_9E42_FCB4E979D673">
					<model ea_localid="2" type="Class" name="Base_module_model"/>
					<role visibility="Public" targetScope="instance"/>
					<type aggregation="none" containment="Unspecified"/>
					<constraints/>
					<modifiers isOrdered="false" changeable="none" isNavigable="true"/>
					<style value="Union=0;Derived=0;AllowDuplicates=0;"/>
					<documentation/>
					<xrefs/>
					<tags/>
				</target>
				<model ea_localid="4"/>
				<properties ea_type="Generalization" direction="Source -&gt; Destination"/>
				<parameterSubstitutions/>
				<documentation/>
				<appearance linemode="3" linecolor="-1" linewidth="0" seqno="0" headStyle="0" lineStyle="0"/>
				<labels/>
				<extendedProperties virtualInheritance="0"/>
				<style/>
				<xrefs/>
				<tags/>
			</connector>
			<connector xmi:idref="EAID_793022EB_77B9_4213_A438_6A06C0D9B3BC">
				<source xmi:idref="EAID_54F7932F_45C9_4ede_90D6_BF7466C1253D">
					<model ea_localid="5" type="Class" name="Udm_library_model"/>
					<role visibility="Public" targetScope="instance"/>
					<type aggregation="none" containment="Unspecified"/>
					<constraints/>
					<modifiers isOrdered="false" changeable="none" isNavigable="false"/>
					<style value="Union=0;Derived=0;AllowDuplicates=0;"/>
					<documentation/>
					<xrefs/>
					<tags/>
				</source>
				<target xmi:idref="EAID_068ADAEC_3A78_4087_9E42_FCB4E979D673">
					<model ea_localid="2" type="Class" name="Base_module_model"/>
					<role visibility="Public" targetScope="instance"/>
					<type aggregation="none" containment="Unspecified"/>
					<constraints/>
					<modifiers isOrdered="false" changeable="none" isNavigable="true"/>
					<style value="Union=0;Derived=0;AllowDuplicates=0;"/>
					<documentation/>
					<xrefs/>
					<tags/>
				</target>
				<model ea_localid="3"/>
				<properties ea_type="Generalization" direction="Source -&gt; Destination"/>
				<parameterSubstitutions/>
				<documentation/>
				<appearance linemode="3" linecolor="-1" linewidth="0" seqno="0" headStyle="0" lineStyle="0"/>
				<labels/>
				<extendedProperties virtualInheritance="0"/>
				<style/>
				<xrefs/>
				<tags/>
			</connector>
			<connector xmi:idref="EAID_955DC0D8_98C4_4c2f_8B31_6BE9FFDB6F84">
				<source xmi:idref="EAID_B4CF4987_0466_4db7_B945_20CEE3E6CAA1">
					<model ea_localid="4" type="Class" name="Udm_microsites_model"/>
					<role visibility="Public" targetScope="instance"/>
					<type aggregation="none" containment="Unspecified"/>
					<constraints/>
					<modifiers isOrdered="false" changeable="none" isNavigable="false"/>
					<style value="Union=0;Derived=0;AllowDuplicates=0;"/>
					<documentation/>
					<xrefs/>
					<tags/>
				</source>
				<target xmi:idref="EAID_068ADAEC_3A78_4087_9E42_FCB4E979D673">
					<model ea_localid="2" type="Class" name="Base_module_model"/>
					<role visibility="Public" targetScope="instance"/>
					<type aggregation="none" containment="Unspecified"/>
					<constraints/>
					<modifiers isOrdered="false" changeable="none" isNavigable="true"/>
					<style value="Union=0;Derived=0;AllowDuplicates=0;"/>
					<documentation/>
					<xrefs/>
					<tags/>
				</target>
				<model ea_localid="2"/>
				<properties ea_type="Generalization" direction="Source -&gt; Destination"/>
				<parameterSubstitutions/>
				<documentation/>
				<appearance linemode="3" linecolor="-1" linewidth="0" seqno="0" headStyle="0" lineStyle="0"/>
				<labels/>
				<extendedProperties virtualInheritance="0"/>
				<style/>
				<xrefs/>
				<tags/>
			</connector>
			<connector xmi:idref="EAID_9AAFA639_A353_4859_9E80_1C3470211ACE">
				<source xmi:idref="EAID_BD878BBE_4E5D_4d79_B379_E0EA41428A58">
					<model ea_localid="3" type="Class" name="Udm_subsciption"/>
					<role visibility="Public" targetScope="instance"/>
					<type aggregation="none" containment="Unspecified"/>
					<constraints/>
					<modifiers isOrdered="false" changeable="none" isNavigable="false"/>
					<style value="Union=0;Derived=0;AllowDuplicates=0;"/>
					<documentation/>
					<xrefs/>
					<tags/>
				</source>
				<target xmi:idref="EAID_068ADAEC_3A78_4087_9E42_FCB4E979D673">
					<model ea_localid="2" type="Class" name="Base_module_model"/>
					<role visibility="Public" targetScope="instance"/>
					<type aggregation="none" containment="Unspecified"/>
					<constraints/>
					<modifiers isOrdered="false" changeable="none" isNavigable="true"/>
					<style value="Union=0;Derived=0;AllowDuplicates=0;"/>
					<documentation/>
					<xrefs/>
					<tags/>
				</target>
				<model ea_localid="1"/>
				<properties ea_type="Generalization" direction="Source -&gt; Destination"/>
				<parameterSubstitutions/>
				<documentation/>
				<appearance linemode="3" linecolor="-1" linewidth="0" seqno="0" headStyle="0" lineStyle="0"/>
				<labels/>
				<extendedProperties virtualInheritance="0"/>
				<style/>
				<xrefs/>
				<tags/>
			</connector>
		</connectors>
		<primitivetypes>
			<packagedElement xmi:type="uml:Package" xmi:id="EAPrimitiveTypesPackage" name="EA_PrimitiveTypes_Package" visibility="public">
				<packagedElement xmi:type="uml:Package" xmi:id="EAJavaTypesPackage" name="EA_Java_Types_Package" visibility="public">
					<packagedElement xmi:type="uml:PrimitiveType" xmi:id="EAJava_Db_active_rec" name="Db_active_rec" visibility="public"/>
					<packagedElement xmi:type="uml:PrimitiveType" xmi:id="EAJava_void" name="void" visibility="public"/>
					<packagedElement xmi:type="uml:PrimitiveType" xmi:id="EAJava_Array" name="Array" visibility="public"/>
				</packagedElement>
			</packagedElement>
		</primitivetypes>
		<profiles/>
		<diagrams>
			<diagram xmi:id="EAID_E470CDC1_5B9B_48e9_8AC2_E32797D8605F">
				<model package="EAPK_0595F4BC_E9EB_43e9_9C60_143B5E25C705" localID="1" owner="EAPK_0595F4BC_E9EB_43e9_9C60_143B5E25C705"/>
				<properties name="class diagram" type="Logical"/>
				<project author="SatyaAnanya" version="1.0" created="2017-10-15 00:00:00" modified="2017-10-15 10:46:13"/>
				<style1 value="ShowPrivate=1;ShowProtected=1;ShowPublic=1;HideRelationships=0;Locked=0;Border=1;HighlightForeign=1;PackageContents=1;SequenceNotes=0;ScalePrintImage=0;PPgs.cx=2;PPgs.cy=1;DocSize.cx=791;DocSize.cy=1043;ShowDetails=0;Orientation=P;Zoom=100;ShowTags=0;OpParams=1;VisibleAttributeDetail=0;ShowOpRetType=1;ShowIcons=1;CollabNums=0;HideProps=0;ShowReqs=0;ShowCons=0;PaperSize=1;HideParents=0;UseAlias=0;HideAtts=0;HideOps=0;HideStereo=0;HideElemStereo=0;ShowTests=0;ShowMaint=0;ConnectorNotation=UML 2.1;ExplicitNavigability=0;ShowShape=1;AdvancedElementProps=1;AdvancedFeatureProps=1;AdvancedConnectorProps=1;m_bElementClassifier=1;ShowNotes=0;SuppressBrackets=0;SuppConnectorLabels=0;PrintPageHeadFoot=0;ShowAsList=0;"/>
				<style2 value="ExcludeRTF=0;DocAll=0;HideQuals=0;AttPkg=1;ShowTests=0;ShowMaint=0;SuppressFOC=1;MatrixActive=0;SwimlanesActive=1;KanbanActive=0;MatrixLineWidth=1;MatrixLineClr=0;MatrixLocked=0;TConnectorNotation=UML 2.1;TExplicitNavigability=0;AdvancedElementProps=1;AdvancedFeatureProps=1;AdvancedConnectorProps=1;m_bElementClassifier=1;ProfileData=;MDGDgm=;STBLDgm=;ShowNotes=0;VisibleAttributeDetail=0;ShowOpRetType=1;SuppressBrackets=0;SuppConnectorLabels=0;PrintPageHeadFoot=0;ShowAsList=0;SuppressedCompartments=;Theme=:119;SaveTag=2F58C35C;"/>
				<swimlanes value="locked=false;orientation=0;width=0;inbar=false;names=false;color=-1;bold=false;fcol=0;tcol=-1;ofCol=-1;ufCol=-1;hl=0;ufh=0;cls=0;SwimlaneFont=lfh:-13,lfw:0,lfi:0,lfu:0,lfs:0,lfface:Calibri,lfe:0,lfo:0,lfchar:1,lfop:0,lfcp:0,lfq:0,lfpf=0,lfWidth=0;"/>
				<matrixitems value="locked=false;matrixactive=false;swimlanesactive=true;kanbanactive=false;width=1;clrLine=0;"/>
				<extendedProperties/>
				<elements>
					<element geometry="Left=710;Top=280;Right=820;Bottom=350;" subject="EAID_A87C57B9_2DC3_4660_9705_CD3AFB8F7944" seqno="1" style="DUID=C2CEFA99;"/>
					<element geometry="Left=510;Top=274;Right=610;Bottom=344;" subject="EAID_54F7932F_45C9_4ede_90D6_BF7466C1253D" seqno="2" style="DUID=4B6669BB;"/>
					<element geometry="Left=270;Top=274;Right=427;Bottom=344;" subject="EAID_B4CF4987_0466_4db7_B945_20CEE3E6CAA1" seqno="3" style="DUID=348260BE;"/>
					<element geometry="Left=56;Top=285;Right=146;Bottom=355;" subject="EAID_BD878BBE_4E5D_4d79_B379_E0EA41428A58" seqno="4" style="DUID=E20ECCDB;"/>
					<element geometry="Left=328;Top=49;Right=503;Bottom=171;" subject="EAID_068ADAEC_3A78_4087_9E42_FCB4E979D673" seqno="5" style="DUID=1C96C642;"/>
					<element geometry="SX=0;SY=0;EX=0;EY=0;EDGE=4;$LLB=;LLT=;LMT=;LMB=;LRT=;LRB=;IRHS=;ILHS=;Path=;" subject="EAID_375AE998_D0DD_41a0_88C7_F7C043F48B30" style="Mode=3;EOID=1C96C642;SOID=C2CEFA99;Color=-1;LWidth=0;Hidden=0;"/>
					<element geometry="SX=0;SY=0;EX=0;EY=0;EDGE=1;$LLB=;LLT=;LMT=;LMB=;LRT=;LRB=;IRHS=;ILHS=;Path=;" subject="EAID_793022EB_77B9_4213_A438_6A06C0D9B3BC" style="Mode=3;EOID=1C96C642;SOID=4B6669BB;Color=-1;LWidth=0;Hidden=0;"/>
					<element geometry="SX=0;SY=0;EX=0;EY=0;EDGE=1;$LLB=;LLT=;LMT=;LMB=;LRT=;LRB=;IRHS=;ILHS=;Path=;" subject="EAID_955DC0D8_98C4_4c2f_8B31_6BE9FFDB6F84" style="Mode=3;EOID=1C96C642;SOID=348260BE;Color=-1;LWidth=0;Hidden=0;"/>
					<element geometry="SX=0;SY=0;EX=0;EY=0;EDGE=2;$LLB=;LLT=;LMT=;LMB=;LRT=;LRB=;IRHS=;ILHS=;Path=;" subject="EAID_9AAFA639_A353_4859_9E80_1C3470211ACE" style="Mode=3;EOID=1C96C642;SOID=E20ECCDB;Color=-1;LWidth=0;Hidden=0;"/>
				</elements>
			</diagram>
		</diagrams>
	</xmi:Extension>
</xmi:XMI>
