<?xml version="1.0" encoding="UTF-8" standalone="yes"?>
<unit xmlns="http://www.srcML.org/srcML/src" revision="0.9.5" language="Java" filename="D:\AndroidAnalysis\Instrumentation-apps\Signal-Android\src\org\thoughtcrime\securesms\devicelist\DeviceNameProtos.java"><comment type="line">// Generated by the protocol buffer compiler.  DO NOT EDIT!</comment>
<comment type="line">// source: DeviceName.proto</comment>

<package>package <name><name>org</name><operator>.</operator><name>thoughtcrime</name><operator>.</operator><name>securesms</name><operator>.</operator><name>devicelist</name></name>;</package>

<class><specifier>public</specifier> <specifier>final</specifier> class <name>DeviceNameProtos</name> <block>{
  <constructor><specifier>private</specifier> <name>DeviceNameProtos</name><parameter_list>()</parameter_list> <block>{}</block></constructor>
  <function><specifier>public</specifier> <specifier>static</specifier> <type><name>void</name></type> <name>registerAllExtensions</name><parameter_list>(
      <parameter><decl><type><name><name>com</name><operator>.</operator><name>google</name><operator>.</operator><name>protobuf</name><operator>.</operator><name>ExtensionRegistry</name></name></type> <name>registry</name></decl></parameter>)</parameter_list> <block>{
  }</block></function>
  <interface><specifier>public</specifier> interface <name>DeviceNameOrBuilder</name>
      <super><extends>extends <name><name>com</name><operator>.</operator><name>google</name><operator>.</operator><name>protobuf</name><operator>.</operator><name>MessageOrBuilder</name></name></extends></super> <block>{

    <comment type="line">// optional bytes ephemeralPublic = 1;</comment>
    <comment type="block" format="javadoc">/**
     * &lt;code&gt;optional bytes ephemeralPublic = 1;&lt;/code&gt;
     */</comment>
    <function_decl><type><name>boolean</name></type> <name>hasEphemeralPublic</name><parameter_list>()</parameter_list>;</function_decl>
    <comment type="block" format="javadoc">/**
     * &lt;code&gt;optional bytes ephemeralPublic = 1;&lt;/code&gt;
     */</comment>
    <function_decl><type><name><name>com</name><operator>.</operator><name>google</name><operator>.</operator><name>protobuf</name><operator>.</operator><name>ByteString</name></name></type> <name>getEphemeralPublic</name><parameter_list>()</parameter_list>;</function_decl>

    <comment type="line">// optional bytes syntheticIv = 2;</comment>
    <comment type="block" format="javadoc">/**
     * &lt;code&gt;optional bytes syntheticIv = 2;&lt;/code&gt;
     */</comment>
    <function_decl><type><name>boolean</name></type> <name>hasSyntheticIv</name><parameter_list>()</parameter_list>;</function_decl>
    <comment type="block" format="javadoc">/**
     * &lt;code&gt;optional bytes syntheticIv = 2;&lt;/code&gt;
     */</comment>
    <function_decl><type><name><name>com</name><operator>.</operator><name>google</name><operator>.</operator><name>protobuf</name><operator>.</operator><name>ByteString</name></name></type> <name>getSyntheticIv</name><parameter_list>()</parameter_list>;</function_decl>

    <comment type="line">// optional bytes ciphertext = 3;</comment>
    <comment type="block" format="javadoc">/**
     * &lt;code&gt;optional bytes ciphertext = 3;&lt;/code&gt;
     */</comment>
    <function_decl><type><name>boolean</name></type> <name>hasCiphertext</name><parameter_list>()</parameter_list>;</function_decl>
    <comment type="block" format="javadoc">/**
     * &lt;code&gt;optional bytes ciphertext = 3;&lt;/code&gt;
     */</comment>
    <function_decl><type><name><name>com</name><operator>.</operator><name>google</name><operator>.</operator><name>protobuf</name><operator>.</operator><name>ByteString</name></name></type> <name>getCiphertext</name><parameter_list>()</parameter_list>;</function_decl>
  }</block></interface>
  <comment type="block" format="javadoc">/**
   * Protobuf type {@code signalservice.DeviceName}
   */</comment>
  <class><specifier>public</specifier> <specifier>static</specifier> <specifier>final</specifier> class <name>DeviceName</name> <super><extends>extends
      <name><name>com</name><operator>.</operator><name>google</name><operator>.</operator><name>protobuf</name><operator>.</operator><name>GeneratedMessage</name></name></extends>
      <implements>implements <name>DeviceNameOrBuilder</name></implements></super> <block>{
    <comment type="line">// Use DeviceName.newBuilder() to construct.</comment>
    <constructor><specifier>private</specifier> <name>DeviceName</name><parameter_list>(<parameter><decl><type><name><name>com</name><operator>.</operator><name>google</name><operator>.</operator><name>protobuf</name><operator>.</operator><name>GeneratedMessage</name><operator>.</operator><name><name>Builder</name><argument_list type="generic">&lt;<argument><name>?</name></argument>&gt;</argument_list></name></name></type> <name>builder</name></decl></parameter>)</parameter_list> <block>{
      <expr_stmt><expr><call><name>super</name><argument_list>(<argument><expr><name>builder</name></expr></argument>)</argument_list></call></expr>;</expr_stmt>
      <expr_stmt><expr><name><name>this</name><operator>.</operator><name>unknownFields</name></name> <operator>=</operator> <call><name><name>builder</name><operator>.</operator><name>getUnknownFields</name></name><argument_list>()</argument_list></call></expr>;</expr_stmt>
    }</block></constructor>
    <constructor><specifier>private</specifier> <name>DeviceName</name><parameter_list>(<parameter><decl><type><name>boolean</name></type> <name>noInit</name></decl></parameter>)</parameter_list> <block>{ <expr_stmt><expr><name><name>this</name><operator>.</operator><name>unknownFields</name></name> <operator>=</operator> <call><name><name>com</name><operator>.</operator><name>google</name><operator>.</operator><name>protobuf</name><operator>.</operator><name>UnknownFieldSet</name><operator>.</operator><name>getDefaultInstance</name></name><argument_list>()</argument_list></call></expr>;</expr_stmt> }</block></constructor>

    <decl_stmt><decl><specifier>private</specifier> <specifier>static</specifier> <type><specifier>final</specifier> <name>DeviceName</name></type> <name>defaultInstance</name></decl>;</decl_stmt>
    <function><specifier>public</specifier> <specifier>static</specifier> <type><name>DeviceName</name></type> <name>getDefaultInstance</name><parameter_list>()</parameter_list> <block>{
      <return>return <expr><name>defaultInstance</name></expr>;</return>
    }</block></function>

    <function><specifier>public</specifier> <type><name>DeviceName</name></type> <name>getDefaultInstanceForType</name><parameter_list>()</parameter_list> <block>{
      <return>return <expr><name>defaultInstance</name></expr>;</return>
    }</block></function>

    <decl_stmt><decl><specifier>private</specifier> <type><specifier>final</specifier> <name><name>com</name><operator>.</operator><name>google</name><operator>.</operator><name>protobuf</name><operator>.</operator><name>UnknownFieldSet</name></name></type> <name>unknownFields</name></decl>;</decl_stmt>
    <function><annotation>@<name><name>java</name><operator>.</operator><name>lang</name><operator>.</operator><name>Override</name></name></annotation>
    <specifier>public</specifier> <specifier>final</specifier> <type><name><name>com</name><operator>.</operator><name>google</name><operator>.</operator><name>protobuf</name><operator>.</operator><name>UnknownFieldSet</name></name></type>
        <name>getUnknownFields</name><parameter_list>()</parameter_list> <block>{
      <return>return <expr><name><name>this</name><operator>.</operator><name>unknownFields</name></name></expr>;</return>
    }</block></function>
    <constructor><specifier>private</specifier> <name>DeviceName</name><parameter_list>(
        <parameter><decl><type><name><name>com</name><operator>.</operator><name>google</name><operator>.</operator><name>protobuf</name><operator>.</operator><name>CodedInputStream</name></name></type> <name>input</name></decl></parameter>,
        <parameter><decl><type><name><name>com</name><operator>.</operator><name>google</name><operator>.</operator><name>protobuf</name><operator>.</operator><name>ExtensionRegistryLite</name></name></type> <name>extensionRegistry</name></decl></parameter>)</parameter_list>
        <throws>throws <argument><expr><name><name>com</name><operator>.</operator><name>google</name><operator>.</operator><name>protobuf</name><operator>.</operator><name>InvalidProtocolBufferException</name></name></expr></argument></throws> <block>{
      <expr_stmt><expr><call><name>initFields</name><argument_list>()</argument_list></call></expr>;</expr_stmt>
      <decl_stmt><decl><type><name>int</name></type> <name>mutable_bitField0_</name> <init>= <expr><literal type="number">0</literal></expr></init></decl>;</decl_stmt>
      <decl_stmt><decl><type><name><name>com</name><operator>.</operator><name>google</name><operator>.</operator><name>protobuf</name><operator>.</operator><name>UnknownFieldSet</name><operator>.</operator><name>Builder</name></name></type> <name>unknownFields</name> <init>=
          <expr><call><name><name>com</name><operator>.</operator><name>google</name><operator>.</operator><name>protobuf</name><operator>.</operator><name>UnknownFieldSet</name><operator>.</operator><name>newBuilder</name></name><argument_list>()</argument_list></call></expr></init></decl>;</decl_stmt>
      <try>try <block>{
        <decl_stmt><decl><type><name>boolean</name></type> <name>done</name> <init>= <expr><literal type="boolean">false</literal></expr></init></decl>;</decl_stmt>
        <while>while <condition>(<expr><operator>!</operator><name>done</name></expr>)</condition> <block>{
          <decl_stmt><decl><type><name>int</name></type> <name>tag</name> <init>= <expr><call><name><name>input</name><operator>.</operator><name>readTag</name></name><argument_list>()</argument_list></call></expr></init></decl>;</decl_stmt>
          <switch>switch <condition>(<expr><name>tag</name></expr>)</condition> <block>{
            <case>case <expr><literal type="number">0</literal></expr>:</case>
              <expr_stmt><expr><name>done</name> <operator>=</operator> <literal type="boolean">true</literal></expr>;</expr_stmt>
              <break>break;</break>
            <default>default:</default> <block>{
              <if>if <condition>(<expr><operator>!</operator><call><name>parseUnknownField</name><argument_list>(<argument><expr><name>input</name></expr></argument>, <argument><expr><name>unknownFields</name></expr></argument>,
                                     <argument><expr><name>extensionRegistry</name></expr></argument>, <argument><expr><name>tag</name></expr></argument>)</argument_list></call></expr>)</condition><then> <block>{
                <expr_stmt><expr><name>done</name> <operator>=</operator> <literal type="boolean">true</literal></expr>;</expr_stmt>
              }</block></then></if>
              <break>break;</break>
            }</block>
            <case>case <expr><literal type="number">10</literal></expr>:</case> <block>{
              <expr_stmt><expr><name>bitField0_</name> <operator>|=</operator> <literal type="number">0x00000001</literal></expr>;</expr_stmt>
              <expr_stmt><expr><name>ephemeralPublic_</name> <operator>=</operator> <call><name><name>input</name><operator>.</operator><name>readBytes</name></name><argument_list>()</argument_list></call></expr>;</expr_stmt>
              <break>break;</break>
            }</block>
            <case>case <expr><literal type="number">18</literal></expr>:</case> <block>{
              <expr_stmt><expr><name>bitField0_</name> <operator>|=</operator> <literal type="number">0x00000002</literal></expr>;</expr_stmt>
              <expr_stmt><expr><name>syntheticIv_</name> <operator>=</operator> <call><name><name>input</name><operator>.</operator><name>readBytes</name></name><argument_list>()</argument_list></call></expr>;</expr_stmt>
              <break>break;</break>
            }</block>
            <case>case <expr><literal type="number">26</literal></expr>:</case> <block>{
              <expr_stmt><expr><name>bitField0_</name> <operator>|=</operator> <literal type="number">0x00000004</literal></expr>;</expr_stmt>
              <expr_stmt><expr><name>ciphertext_</name> <operator>=</operator> <call><name><name>input</name><operator>.</operator><name>readBytes</name></name><argument_list>()</argument_list></call></expr>;</expr_stmt>
              <break>break;</break>
            }</block>
          }</block></switch>
        }</block></while>
      }</block> <catch>catch <parameter_list>(<parameter><decl><type><name><name>com</name><operator>.</operator><name>google</name><operator>.</operator><name>protobuf</name><operator>.</operator><name>InvalidProtocolBufferException</name></name></type> <name>e</name></decl></parameter>)</parameter_list> <block>{
        <throw>throw <expr><call><name><name>e</name><operator>.</operator><name>setUnfinishedMessage</name></name><argument_list>(<argument><expr><name>this</name></expr></argument>)</argument_list></call></expr>;</throw>
      }</block></catch> <catch>catch <parameter_list>(<parameter><decl><type><name><name>java</name><operator>.</operator><name>io</name><operator>.</operator><name>IOException</name></name></type> <name>e</name></decl></parameter>)</parameter_list> <block>{
        <throw>throw <expr><operator>new</operator> <call><name><name>com</name><operator>.</operator><name>google</name><operator>.</operator><name>protobuf</name><operator>.</operator><name>InvalidProtocolBufferException</name></name><argument_list>(
            <argument><expr><call><name><name>e</name><operator>.</operator><name>getMessage</name></name><argument_list>()</argument_list></call></expr></argument>)</argument_list></call><operator>.</operator><call><name>setUnfinishedMessage</name><argument_list>(<argument><expr><name>this</name></expr></argument>)</argument_list></call></expr>;</throw>
      }</block></catch> <finally>finally <block>{
        <expr_stmt><expr><name><name>this</name><operator>.</operator><name>unknownFields</name></name> <operator>=</operator> <call><name><name>unknownFields</name><operator>.</operator><name>build</name></name><argument_list>()</argument_list></call></expr>;</expr_stmt>
        <expr_stmt><expr><call><name>makeExtensionsImmutable</name><argument_list>()</argument_list></call></expr>;</expr_stmt>
      }</block></finally></try>
    }</block></constructor>
    <function><specifier>public</specifier> <specifier>static</specifier> <specifier>final</specifier> <type><name><name>com</name><operator>.</operator><name>google</name><operator>.</operator><name>protobuf</name><operator>.</operator><name>Descriptors</name><operator>.</operator><name>Descriptor</name></name></type>
        <name>getDescriptor</name><parameter_list>()</parameter_list> <block>{
      <return>return <expr><name><name>org</name><operator>.</operator><name>thoughtcrime</name><operator>.</operator><name>securesms</name><operator>.</operator><name>devicelist</name><operator>.</operator><name>DeviceNameProtos</name><operator>.</operator><name>internal_static_signalservice_DeviceName_descriptor</name></name></expr>;</return>
    }</block></function>

    <function><specifier>protected</specifier> <type><name><name>com</name><operator>.</operator><name>google</name><operator>.</operator><name>protobuf</name><operator>.</operator><name>GeneratedMessage</name><operator>.</operator><name>FieldAccessorTable</name></name></type>
        <name>internalGetFieldAccessorTable</name><parameter_list>()</parameter_list> <block>{
      <return>return <expr><call><name><name>org</name><operator>.</operator><name>thoughtcrime</name><operator>.</operator><name>securesms</name><operator>.</operator><name>devicelist</name><operator>.</operator><name>DeviceNameProtos</name><operator>.</operator><name>internal_static_signalservice_DeviceName_fieldAccessorTable</name>
          <operator>.</operator><name>ensureFieldAccessorsInitialized</name></name><argument_list>(
              <argument><expr><name><name>org</name><operator>.</operator><name>thoughtcrime</name><operator>.</operator><name>securesms</name><operator>.</operator><name>devicelist</name><operator>.</operator><name>DeviceNameProtos</name><operator>.</operator><name>DeviceName</name><operator>.</operator><name>class</name></name></expr></argument>, <argument><expr><name><name>org</name><operator>.</operator><name>thoughtcrime</name><operator>.</operator><name>securesms</name><operator>.</operator><name>devicelist</name><operator>.</operator><name>DeviceNameProtos</name><operator>.</operator><name>DeviceName</name><operator>.</operator><name>Builder</name><operator>.</operator><name>class</name></name></expr></argument>)</argument_list></call></expr>;</return>
    }</block></function>

    <decl_stmt><decl><specifier>public</specifier> <specifier>static</specifier> <type><name><name>com</name><operator>.</operator><name>google</name><operator>.</operator><name>protobuf</name><operator>.</operator><name><name>Parser</name><argument_list type="generic">&lt;<argument><name>DeviceName</name></argument>&gt;</argument_list></name></name></type> <name>PARSER</name> <init>=
        <expr><operator>new</operator> <class><super><name><name>com</name><operator>.</operator><name>google</name><operator>.</operator><name>protobuf</name><operator>.</operator><name><name>AbstractParser</name><argument_list type="generic">&lt;<argument><name>DeviceName</name></argument>&gt;</argument_list></name></name></super><argument_list>()</argument_list> <block>{
      <function><specifier>public</specifier> <type><name>DeviceName</name></type> <name>parsePartialFrom</name><parameter_list>(
          <parameter><decl><type><name><name>com</name><operator>.</operator><name>google</name><operator>.</operator><name>protobuf</name><operator>.</operator><name>CodedInputStream</name></name></type> <name>input</name></decl></parameter>,
          <parameter><decl><type><name><name>com</name><operator>.</operator><name>google</name><operator>.</operator><name>protobuf</name><operator>.</operator><name>ExtensionRegistryLite</name></name></type> <name>extensionRegistry</name></decl></parameter>)</parameter_list>
          <throws>throws <argument><expr><name><name>com</name><operator>.</operator><name>google</name><operator>.</operator><name>protobuf</name><operator>.</operator><name>InvalidProtocolBufferException</name></name></expr></argument></throws> <block>{
        <return>return <expr><operator>new</operator> <call><name>DeviceName</name><argument_list>(<argument><expr><name>input</name></expr></argument>, <argument><expr><name>extensionRegistry</name></expr></argument>)</argument_list></call></expr>;</return>
      }</block></function>
    }</block></class></expr></init></decl>;</decl_stmt>

    <function><annotation>@<name><name>java</name><operator>.</operator><name>lang</name><operator>.</operator><name>Override</name></name></annotation>
    <specifier>public</specifier> <type><name><name>com</name><operator>.</operator><name>google</name><operator>.</operator><name>protobuf</name><operator>.</operator><name><name>Parser</name><argument_list type="generic">&lt;<argument><name>DeviceName</name></argument>&gt;</argument_list></name></name></type> <name>getParserForType</name><parameter_list>()</parameter_list> <block>{
      <return>return <expr><name>PARSER</name></expr>;</return>
    }</block></function>

    <decl_stmt><decl><specifier>private</specifier> <type><name>int</name></type> <name>bitField0_</name></decl>;</decl_stmt>
    <comment type="line">// optional bytes ephemeralPublic = 1;</comment>
    <decl_stmt><decl><specifier>public</specifier> <specifier>static</specifier> <type><specifier>final</specifier> <name>int</name></type> <name>EPHEMERALPUBLIC_FIELD_NUMBER</name> <init>= <expr><literal type="number">1</literal></expr></init></decl>;</decl_stmt>
    <decl_stmt><decl><specifier>private</specifier> <type><name><name>com</name><operator>.</operator><name>google</name><operator>.</operator><name>protobuf</name><operator>.</operator><name>ByteString</name></name></type> <name>ephemeralPublic_</name></decl>;</decl_stmt>
    <comment type="block" format="javadoc">/**
     * &lt;code&gt;optional bytes ephemeralPublic = 1;&lt;/code&gt;
     */</comment>
    <function><specifier>public</specifier> <type><name>boolean</name></type> <name>hasEphemeralPublic</name><parameter_list>()</parameter_list> <block>{
      <return>return <expr><operator>(</operator><operator>(</operator><name>bitField0_</name> <operator>&amp;</operator> <literal type="number">0x00000001</literal><operator>)</operator> <operator>==</operator> <literal type="number">0x00000001</literal><operator>)</operator></expr>;</return>
    }</block></function>
    <comment type="block" format="javadoc">/**
     * &lt;code&gt;optional bytes ephemeralPublic = 1;&lt;/code&gt;
     */</comment>
    <function><specifier>public</specifier> <type><name><name>com</name><operator>.</operator><name>google</name><operator>.</operator><name>protobuf</name><operator>.</operator><name>ByteString</name></name></type> <name>getEphemeralPublic</name><parameter_list>()</parameter_list> <block>{
      <return>return <expr><name>ephemeralPublic_</name></expr>;</return>
    }</block></function>

    <comment type="line">// optional bytes syntheticIv = 2;</comment>
    <decl_stmt><decl><specifier>public</specifier> <specifier>static</specifier> <type><specifier>final</specifier> <name>int</name></type> <name>SYNTHETICIV_FIELD_NUMBER</name> <init>= <expr><literal type="number">2</literal></expr></init></decl>;</decl_stmt>
    <decl_stmt><decl><specifier>private</specifier> <type><name><name>com</name><operator>.</operator><name>google</name><operator>.</operator><name>protobuf</name><operator>.</operator><name>ByteString</name></name></type> <name>syntheticIv_</name></decl>;</decl_stmt>
    <comment type="block" format="javadoc">/**
     * &lt;code&gt;optional bytes syntheticIv = 2;&lt;/code&gt;
     */</comment>
    <function><specifier>public</specifier> <type><name>boolean</name></type> <name>hasSyntheticIv</name><parameter_list>()</parameter_list> <block>{
      <return>return <expr><operator>(</operator><operator>(</operator><name>bitField0_</name> <operator>&amp;</operator> <literal type="number">0x00000002</literal><operator>)</operator> <operator>==</operator> <literal type="number">0x00000002</literal><operator>)</operator></expr>;</return>
    }</block></function>
    <comment type="block" format="javadoc">/**
     * &lt;code&gt;optional bytes syntheticIv = 2;&lt;/code&gt;
     */</comment>
    <function><specifier>public</specifier> <type><name><name>com</name><operator>.</operator><name>google</name><operator>.</operator><name>protobuf</name><operator>.</operator><name>ByteString</name></name></type> <name>getSyntheticIv</name><parameter_list>()</parameter_list> <block>{
      <return>return <expr><name>syntheticIv_</name></expr>;</return>
    }</block></function>

    <comment type="line">// optional bytes ciphertext = 3;</comment>
    <decl_stmt><decl><specifier>public</specifier> <specifier>static</specifier> <type><specifier>final</specifier> <name>int</name></type> <name>CIPHERTEXT_FIELD_NUMBER</name> <init>= <expr><literal type="number">3</literal></expr></init></decl>;</decl_stmt>
    <decl_stmt><decl><specifier>private</specifier> <type><name><name>com</name><operator>.</operator><name>google</name><operator>.</operator><name>protobuf</name><operator>.</operator><name>ByteString</name></name></type> <name>ciphertext_</name></decl>;</decl_stmt>
    <comment type="block" format="javadoc">/**
     * &lt;code&gt;optional bytes ciphertext = 3;&lt;/code&gt;
     */</comment>
    <function><specifier>public</specifier> <type><name>boolean</name></type> <name>hasCiphertext</name><parameter_list>()</parameter_list> <block>{
      <return>return <expr><operator>(</operator><operator>(</operator><name>bitField0_</name> <operator>&amp;</operator> <literal type="number">0x00000004</literal><operator>)</operator> <operator>==</operator> <literal type="number">0x00000004</literal><operator>)</operator></expr>;</return>
    }</block></function>
    <comment type="block" format="javadoc">/**
     * &lt;code&gt;optional bytes ciphertext = 3;&lt;/code&gt;
     */</comment>
    <function><specifier>public</specifier> <type><name><name>com</name><operator>.</operator><name>google</name><operator>.</operator><name>protobuf</name><operator>.</operator><name>ByteString</name></name></type> <name>getCiphertext</name><parameter_list>()</parameter_list> <block>{
      <return>return <expr><name>ciphertext_</name></expr>;</return>
    }</block></function>

    <function><specifier>private</specifier> <type><name>void</name></type> <name>initFields</name><parameter_list>()</parameter_list> <block>{
      <expr_stmt><expr><name>ephemeralPublic_</name> <operator>=</operator> <name><name>com</name><operator>.</operator><name>google</name><operator>.</operator><name>protobuf</name><operator>.</operator><name>ByteString</name><operator>.</operator><name>EMPTY</name></name></expr>;</expr_stmt>
      <expr_stmt><expr><name>syntheticIv_</name> <operator>=</operator> <name><name>com</name><operator>.</operator><name>google</name><operator>.</operator><name>protobuf</name><operator>.</operator><name>ByteString</name><operator>.</operator><name>EMPTY</name></name></expr>;</expr_stmt>
      <expr_stmt><expr><name>ciphertext_</name> <operator>=</operator> <name><name>com</name><operator>.</operator><name>google</name><operator>.</operator><name>protobuf</name><operator>.</operator><name>ByteString</name><operator>.</operator><name>EMPTY</name></name></expr>;</expr_stmt>
    }</block></function>
    <decl_stmt><decl><specifier>private</specifier> <type><name>byte</name></type> <name>memoizedIsInitialized</name> <init>= <expr><operator>-</operator><literal type="number">1</literal></expr></init></decl>;</decl_stmt>
    <function><specifier>public</specifier> <specifier>final</specifier> <type><name>boolean</name></type> <name>isInitialized</name><parameter_list>()</parameter_list> <block>{
      <decl_stmt><decl><type><name>byte</name></type> <name>isInitialized</name> <init>= <expr><name>memoizedIsInitialized</name></expr></init></decl>;</decl_stmt>
      <if>if <condition>(<expr><name>isInitialized</name> <operator>!=</operator> <operator>-</operator><literal type="number">1</literal></expr>)</condition><then> <block type="pseudo"><return>return <expr><name>isInitialized</name> <operator>==</operator> <literal type="number">1</literal></expr>;</return></block></then></if>

      <expr_stmt><expr><name>memoizedIsInitialized</name> <operator>=</operator> <literal type="number">1</literal></expr>;</expr_stmt>
      <return>return <expr><literal type="boolean">true</literal></expr>;</return>
    }</block></function>

    <function><specifier>public</specifier> <type><name>void</name></type> <name>writeTo</name><parameter_list>(<parameter><decl><type><name><name>com</name><operator>.</operator><name>google</name><operator>.</operator><name>protobuf</name><operator>.</operator><name>CodedOutputStream</name></name></type> <name>output</name></decl></parameter>)</parameter_list>
                        <throws>throws <argument><expr><name><name>java</name><operator>.</operator><name>io</name><operator>.</operator><name>IOException</name></name></expr></argument></throws> <block>{
      <expr_stmt><expr><call><name>getSerializedSize</name><argument_list>()</argument_list></call></expr>;</expr_stmt>
      <if>if <condition>(<expr><operator>(</operator><operator>(</operator><name>bitField0_</name> <operator>&amp;</operator> <literal type="number">0x00000001</literal><operator>)</operator> <operator>==</operator> <literal type="number">0x00000001</literal><operator>)</operator></expr>)</condition><then> <block>{
        <expr_stmt><expr><call><name><name>output</name><operator>.</operator><name>writeBytes</name></name><argument_list>(<argument><expr><literal type="number">1</literal></expr></argument>, <argument><expr><name>ephemeralPublic_</name></expr></argument>)</argument_list></call></expr>;</expr_stmt>
      }</block></then></if>
      <if>if <condition>(<expr><operator>(</operator><operator>(</operator><name>bitField0_</name> <operator>&amp;</operator> <literal type="number">0x00000002</literal><operator>)</operator> <operator>==</operator> <literal type="number">0x00000002</literal><operator>)</operator></expr>)</condition><then> <block>{
        <expr_stmt><expr><call><name><name>output</name><operator>.</operator><name>writeBytes</name></name><argument_list>(<argument><expr><literal type="number">2</literal></expr></argument>, <argument><expr><name>syntheticIv_</name></expr></argument>)</argument_list></call></expr>;</expr_stmt>
      }</block></then></if>
      <if>if <condition>(<expr><operator>(</operator><operator>(</operator><name>bitField0_</name> <operator>&amp;</operator> <literal type="number">0x00000004</literal><operator>)</operator> <operator>==</operator> <literal type="number">0x00000004</literal><operator>)</operator></expr>)</condition><then> <block>{
        <expr_stmt><expr><call><name><name>output</name><operator>.</operator><name>writeBytes</name></name><argument_list>(<argument><expr><literal type="number">3</literal></expr></argument>, <argument><expr><name>ciphertext_</name></expr></argument>)</argument_list></call></expr>;</expr_stmt>
      }</block></then></if>
      <expr_stmt><expr><call><name>getUnknownFields</name><argument_list>()</argument_list></call><operator>.</operator><call><name>writeTo</name><argument_list>(<argument><expr><name>output</name></expr></argument>)</argument_list></call></expr>;</expr_stmt>
    }</block></function>

    <decl_stmt><decl><specifier>private</specifier> <type><name>int</name></type> <name>memoizedSerializedSize</name> <init>= <expr><operator>-</operator><literal type="number">1</literal></expr></init></decl>;</decl_stmt>
    <function><specifier>public</specifier> <type><name>int</name></type> <name>getSerializedSize</name><parameter_list>()</parameter_list> <block>{
      <decl_stmt><decl><type><name>int</name></type> <name>size</name> <init>= <expr><name>memoizedSerializedSize</name></expr></init></decl>;</decl_stmt>
      <if>if <condition>(<expr><name>size</name> <operator>!=</operator> <operator>-</operator><literal type="number">1</literal></expr>)</condition><then> <block type="pseudo"><return>return <expr><name>size</name></expr>;</return></block></then></if>

      <expr_stmt><expr><name>size</name> <operator>=</operator> <literal type="number">0</literal></expr>;</expr_stmt>
      <if>if <condition>(<expr><operator>(</operator><operator>(</operator><name>bitField0_</name> <operator>&amp;</operator> <literal type="number">0x00000001</literal><operator>)</operator> <operator>==</operator> <literal type="number">0x00000001</literal><operator>)</operator></expr>)</condition><then> <block>{
        <expr_stmt><expr><name>size</name> <operator>+=</operator> <call><name><name>com</name><operator>.</operator><name>google</name><operator>.</operator><name>protobuf</name><operator>.</operator><name>CodedOutputStream</name>
          <operator>.</operator><name>computeBytesSize</name></name><argument_list>(<argument><expr><literal type="number">1</literal></expr></argument>, <argument><expr><name>ephemeralPublic_</name></expr></argument>)</argument_list></call></expr>;</expr_stmt>
      }</block></then></if>
      <if>if <condition>(<expr><operator>(</operator><operator>(</operator><name>bitField0_</name> <operator>&amp;</operator> <literal type="number">0x00000002</literal><operator>)</operator> <operator>==</operator> <literal type="number">0x00000002</literal><operator>)</operator></expr>)</condition><then> <block>{
        <expr_stmt><expr><name>size</name> <operator>+=</operator> <call><name><name>com</name><operator>.</operator><name>google</name><operator>.</operator><name>protobuf</name><operator>.</operator><name>CodedOutputStream</name>
          <operator>.</operator><name>computeBytesSize</name></name><argument_list>(<argument><expr><literal type="number">2</literal></expr></argument>, <argument><expr><name>syntheticIv_</name></expr></argument>)</argument_list></call></expr>;</expr_stmt>
      }</block></then></if>
      <if>if <condition>(<expr><operator>(</operator><operator>(</operator><name>bitField0_</name> <operator>&amp;</operator> <literal type="number">0x00000004</literal><operator>)</operator> <operator>==</operator> <literal type="number">0x00000004</literal><operator>)</operator></expr>)</condition><then> <block>{
        <expr_stmt><expr><name>size</name> <operator>+=</operator> <call><name><name>com</name><operator>.</operator><name>google</name><operator>.</operator><name>protobuf</name><operator>.</operator><name>CodedOutputStream</name>
          <operator>.</operator><name>computeBytesSize</name></name><argument_list>(<argument><expr><literal type="number">3</literal></expr></argument>, <argument><expr><name>ciphertext_</name></expr></argument>)</argument_list></call></expr>;</expr_stmt>
      }</block></then></if>
      <expr_stmt><expr><name>size</name> <operator>+=</operator> <call><name>getUnknownFields</name><argument_list>()</argument_list></call><operator>.</operator><call><name>getSerializedSize</name><argument_list>()</argument_list></call></expr>;</expr_stmt>
      <expr_stmt><expr><name>memoizedSerializedSize</name> <operator>=</operator> <name>size</name></expr>;</expr_stmt>
      <return>return <expr><name>size</name></expr>;</return>
    }</block></function>

    <decl_stmt><decl><specifier>private</specifier> <specifier>static</specifier> <type><specifier>final</specifier> <name>long</name></type> <name>serialVersionUID</name> <init>= <expr><literal type="number">0L</literal></expr></init></decl>;</decl_stmt>
    <function><annotation>@<name><name>java</name><operator>.</operator><name>lang</name><operator>.</operator><name>Override</name></name></annotation>
    <specifier>protected</specifier> <type><name><name>java</name><operator>.</operator><name>lang</name><operator>.</operator><name>Object</name></name></type> <name>writeReplace</name><parameter_list>()</parameter_list>
        <throws>throws <argument><expr><name><name>java</name><operator>.</operator><name>io</name><operator>.</operator><name>ObjectStreamException</name></name></expr></argument></throws> <block>{
      <return>return <expr><call><name><name>super</name><operator>.</operator><name>writeReplace</name></name><argument_list>()</argument_list></call></expr>;</return>
    }</block></function>

    <function><specifier>public</specifier> <specifier>static</specifier> <type><name><name>org</name><operator>.</operator><name>thoughtcrime</name><operator>.</operator><name>securesms</name><operator>.</operator><name>devicelist</name><operator>.</operator><name>DeviceNameProtos</name><operator>.</operator><name>DeviceName</name></name></type> <name>parseFrom</name><parameter_list>(
        <parameter><decl><type><name><name>com</name><operator>.</operator><name>google</name><operator>.</operator><name>protobuf</name><operator>.</operator><name>ByteString</name></name></type> <name>data</name></decl></parameter>)</parameter_list>
        <throws>throws <argument><expr><name><name>com</name><operator>.</operator><name>google</name><operator>.</operator><name>protobuf</name><operator>.</operator><name>InvalidProtocolBufferException</name></name></expr></argument></throws> <block>{
      <return>return <expr><call><name><name>PARSER</name><operator>.</operator><name>parseFrom</name></name><argument_list>(<argument><expr><name>data</name></expr></argument>)</argument_list></call></expr>;</return>
    }</block></function>
    <function><specifier>public</specifier> <specifier>static</specifier> <type><name><name>org</name><operator>.</operator><name>thoughtcrime</name><operator>.</operator><name>securesms</name><operator>.</operator><name>devicelist</name><operator>.</operator><name>DeviceNameProtos</name><operator>.</operator><name>DeviceName</name></name></type> <name>parseFrom</name><parameter_list>(
        <parameter><decl><type><name><name>com</name><operator>.</operator><name>google</name><operator>.</operator><name>protobuf</name><operator>.</operator><name>ByteString</name></name></type> <name>data</name></decl></parameter>,
        <parameter><decl><type><name><name>com</name><operator>.</operator><name>google</name><operator>.</operator><name>protobuf</name><operator>.</operator><name>ExtensionRegistryLite</name></name></type> <name>extensionRegistry</name></decl></parameter>)</parameter_list>
        <throws>throws <argument><expr><name><name>com</name><operator>.</operator><name>google</name><operator>.</operator><name>protobuf</name><operator>.</operator><name>InvalidProtocolBufferException</name></name></expr></argument></throws> <block>{
      <return>return <expr><call><name><name>PARSER</name><operator>.</operator><name>parseFrom</name></name><argument_list>(<argument><expr><name>data</name></expr></argument>, <argument><expr><name>extensionRegistry</name></expr></argument>)</argument_list></call></expr>;</return>
    }</block></function>
    <function><specifier>public</specifier> <specifier>static</specifier> <type><name><name>org</name><operator>.</operator><name>thoughtcrime</name><operator>.</operator><name>securesms</name><operator>.</operator><name>devicelist</name><operator>.</operator><name>DeviceNameProtos</name><operator>.</operator><name>DeviceName</name></name></type> <name>parseFrom</name><parameter_list>(<parameter><decl><type><name><name>byte</name><index>[]</index></name></type> <name>data</name></decl></parameter>)</parameter_list>
        <throws>throws <argument><expr><name><name>com</name><operator>.</operator><name>google</name><operator>.</operator><name>protobuf</name><operator>.</operator><name>InvalidProtocolBufferException</name></name></expr></argument></throws> <block>{
      <return>return <expr><call><name><name>PARSER</name><operator>.</operator><name>parseFrom</name></name><argument_list>(<argument><expr><name>data</name></expr></argument>)</argument_list></call></expr>;</return>
    }</block></function>
    <function><specifier>public</specifier> <specifier>static</specifier> <type><name><name>org</name><operator>.</operator><name>thoughtcrime</name><operator>.</operator><name>securesms</name><operator>.</operator><name>devicelist</name><operator>.</operator><name>DeviceNameProtos</name><operator>.</operator><name>DeviceName</name></name></type> <name>parseFrom</name><parameter_list>(
        <parameter><decl><type><name><name>byte</name><index>[]</index></name></type> <name>data</name></decl></parameter>,
        <parameter><decl><type><name><name>com</name><operator>.</operator><name>google</name><operator>.</operator><name>protobuf</name><operator>.</operator><name>ExtensionRegistryLite</name></name></type> <name>extensionRegistry</name></decl></parameter>)</parameter_list>
        <throws>throws <argument><expr><name><name>com</name><operator>.</operator><name>google</name><operator>.</operator><name>protobuf</name><operator>.</operator><name>InvalidProtocolBufferException</name></name></expr></argument></throws> <block>{
      <return>return <expr><call><name><name>PARSER</name><operator>.</operator><name>parseFrom</name></name><argument_list>(<argument><expr><name>data</name></expr></argument>, <argument><expr><name>extensionRegistry</name></expr></argument>)</argument_list></call></expr>;</return>
    }</block></function>
    <function><specifier>public</specifier> <specifier>static</specifier> <type><name><name>org</name><operator>.</operator><name>thoughtcrime</name><operator>.</operator><name>securesms</name><operator>.</operator><name>devicelist</name><operator>.</operator><name>DeviceNameProtos</name><operator>.</operator><name>DeviceName</name></name></type> <name>parseFrom</name><parameter_list>(<parameter><decl><type><name><name>java</name><operator>.</operator><name>io</name><operator>.</operator><name>InputStream</name></name></type> <name>input</name></decl></parameter>)</parameter_list>
        <throws>throws <argument><expr><name><name>java</name><operator>.</operator><name>io</name><operator>.</operator><name>IOException</name></name></expr></argument></throws> <block>{
      <return>return <expr><call><name><name>PARSER</name><operator>.</operator><name>parseFrom</name></name><argument_list>(<argument><expr><name>input</name></expr></argument>)</argument_list></call></expr>;</return>
    }</block></function>
    <function><specifier>public</specifier> <specifier>static</specifier> <type><name><name>org</name><operator>.</operator><name>thoughtcrime</name><operator>.</operator><name>securesms</name><operator>.</operator><name>devicelist</name><operator>.</operator><name>DeviceNameProtos</name><operator>.</operator><name>DeviceName</name></name></type> <name>parseFrom</name><parameter_list>(
        <parameter><decl><type><name><name>java</name><operator>.</operator><name>io</name><operator>.</operator><name>InputStream</name></name></type> <name>input</name></decl></parameter>,
        <parameter><decl><type><name><name>com</name><operator>.</operator><name>google</name><operator>.</operator><name>protobuf</name><operator>.</operator><name>ExtensionRegistryLite</name></name></type> <name>extensionRegistry</name></decl></parameter>)</parameter_list>
        <throws>throws <argument><expr><name><name>java</name><operator>.</operator><name>io</name><operator>.</operator><name>IOException</name></name></expr></argument></throws> <block>{
      <return>return <expr><call><name><name>PARSER</name><operator>.</operator><name>parseFrom</name></name><argument_list>(<argument><expr><name>input</name></expr></argument>, <argument><expr><name>extensionRegistry</name></expr></argument>)</argument_list></call></expr>;</return>
    }</block></function>
    <function><specifier>public</specifier> <specifier>static</specifier> <type><name><name>org</name><operator>.</operator><name>thoughtcrime</name><operator>.</operator><name>securesms</name><operator>.</operator><name>devicelist</name><operator>.</operator><name>DeviceNameProtos</name><operator>.</operator><name>DeviceName</name></name></type> <name>parseDelimitedFrom</name><parameter_list>(<parameter><decl><type><name><name>java</name><operator>.</operator><name>io</name><operator>.</operator><name>InputStream</name></name></type> <name>input</name></decl></parameter>)</parameter_list>
        <throws>throws <argument><expr><name><name>java</name><operator>.</operator><name>io</name><operator>.</operator><name>IOException</name></name></expr></argument></throws> <block>{
      <return>return <expr><call><name><name>PARSER</name><operator>.</operator><name>parseDelimitedFrom</name></name><argument_list>(<argument><expr><name>input</name></expr></argument>)</argument_list></call></expr>;</return>
    }</block></function>
    <function><specifier>public</specifier> <specifier>static</specifier> <type><name><name>org</name><operator>.</operator><name>thoughtcrime</name><operator>.</operator><name>securesms</name><operator>.</operator><name>devicelist</name><operator>.</operator><name>DeviceNameProtos</name><operator>.</operator><name>DeviceName</name></name></type> <name>parseDelimitedFrom</name><parameter_list>(
        <parameter><decl><type><name><name>java</name><operator>.</operator><name>io</name><operator>.</operator><name>InputStream</name></name></type> <name>input</name></decl></parameter>,
        <parameter><decl><type><name><name>com</name><operator>.</operator><name>google</name><operator>.</operator><name>protobuf</name><operator>.</operator><name>ExtensionRegistryLite</name></name></type> <name>extensionRegistry</name></decl></parameter>)</parameter_list>
        <throws>throws <argument><expr><name><name>java</name><operator>.</operator><name>io</name><operator>.</operator><name>IOException</name></name></expr></argument></throws> <block>{
      <return>return <expr><call><name><name>PARSER</name><operator>.</operator><name>parseDelimitedFrom</name></name><argument_list>(<argument><expr><name>input</name></expr></argument>, <argument><expr><name>extensionRegistry</name></expr></argument>)</argument_list></call></expr>;</return>
    }</block></function>
    <function><specifier>public</specifier> <specifier>static</specifier> <type><name><name>org</name><operator>.</operator><name>thoughtcrime</name><operator>.</operator><name>securesms</name><operator>.</operator><name>devicelist</name><operator>.</operator><name>DeviceNameProtos</name><operator>.</operator><name>DeviceName</name></name></type> <name>parseFrom</name><parameter_list>(
        <parameter><decl><type><name><name>com</name><operator>.</operator><name>google</name><operator>.</operator><name>protobuf</name><operator>.</operator><name>CodedInputStream</name></name></type> <name>input</name></decl></parameter>)</parameter_list>
        <throws>throws <argument><expr><name><name>java</name><operator>.</operator><name>io</name><operator>.</operator><name>IOException</name></name></expr></argument></throws> <block>{
      <return>return <expr><call><name><name>PARSER</name><operator>.</operator><name>parseFrom</name></name><argument_list>(<argument><expr><name>input</name></expr></argument>)</argument_list></call></expr>;</return>
    }</block></function>
    <function><specifier>public</specifier> <specifier>static</specifier> <type><name><name>org</name><operator>.</operator><name>thoughtcrime</name><operator>.</operator><name>securesms</name><operator>.</operator><name>devicelist</name><operator>.</operator><name>DeviceNameProtos</name><operator>.</operator><name>DeviceName</name></name></type> <name>parseFrom</name><parameter_list>(
        <parameter><decl><type><name><name>com</name><operator>.</operator><name>google</name><operator>.</operator><name>protobuf</name><operator>.</operator><name>CodedInputStream</name></name></type> <name>input</name></decl></parameter>,
        <parameter><decl><type><name><name>com</name><operator>.</operator><name>google</name><operator>.</operator><name>protobuf</name><operator>.</operator><name>ExtensionRegistryLite</name></name></type> <name>extensionRegistry</name></decl></parameter>)</parameter_list>
        <throws>throws <argument><expr><name><name>java</name><operator>.</operator><name>io</name><operator>.</operator><name>IOException</name></name></expr></argument></throws> <block>{
      <return>return <expr><call><name><name>PARSER</name><operator>.</operator><name>parseFrom</name></name><argument_list>(<argument><expr><name>input</name></expr></argument>, <argument><expr><name>extensionRegistry</name></expr></argument>)</argument_list></call></expr>;</return>
    }</block></function>

    <function><specifier>public</specifier> <specifier>static</specifier> <type><name>Builder</name></type> <name>newBuilder</name><parameter_list>()</parameter_list> <block>{ <return>return <expr><call><name><name>Builder</name><operator>.</operator><name>create</name></name><argument_list>()</argument_list></call></expr>;</return> }</block></function>
    <function><specifier>public</specifier> <type><name>Builder</name></type> <name>newBuilderForType</name><parameter_list>()</parameter_list> <block>{ <return>return <expr><call><name>newBuilder</name><argument_list>()</argument_list></call></expr>;</return> }</block></function>
    <function><specifier>public</specifier> <specifier>static</specifier> <type><name>Builder</name></type> <name>newBuilder</name><parameter_list>(<parameter><decl><type><name><name>org</name><operator>.</operator><name>thoughtcrime</name><operator>.</operator><name>securesms</name><operator>.</operator><name>devicelist</name><operator>.</operator><name>DeviceNameProtos</name><operator>.</operator><name>DeviceName</name></name></type> <name>prototype</name></decl></parameter>)</parameter_list> <block>{
      <return>return <expr><call><name>newBuilder</name><argument_list>()</argument_list></call><operator>.</operator><call><name>mergeFrom</name><argument_list>(<argument><expr><name>prototype</name></expr></argument>)</argument_list></call></expr>;</return>
    }</block></function>
    <function><specifier>public</specifier> <type><name>Builder</name></type> <name>toBuilder</name><parameter_list>()</parameter_list> <block>{ <return>return <expr><call><name>newBuilder</name><argument_list>(<argument><expr><name>this</name></expr></argument>)</argument_list></call></expr>;</return> }</block></function>

    <function><annotation>@<name><name>java</name><operator>.</operator><name>lang</name><operator>.</operator><name>Override</name></name></annotation>
    <specifier>protected</specifier> <type><name>Builder</name></type> <name>newBuilderForType</name><parameter_list>(
        <parameter><decl><type><name><name>com</name><operator>.</operator><name>google</name><operator>.</operator><name>protobuf</name><operator>.</operator><name>GeneratedMessage</name><operator>.</operator><name>BuilderParent</name></name></type> <name>parent</name></decl></parameter>)</parameter_list> <block>{
      <decl_stmt><decl><type><name>Builder</name></type> <name>builder</name> <init>= <expr><operator>new</operator> <call><name>Builder</name><argument_list>(<argument><expr><name>parent</name></expr></argument>)</argument_list></call></expr></init></decl>;</decl_stmt>
      <return>return <expr><name>builder</name></expr>;</return>
    }</block></function>
    <comment type="block" format="javadoc">/**
     * Protobuf type {@code signalservice.DeviceName}
     */</comment>
    <class><specifier>public</specifier> <specifier>static</specifier> <specifier>final</specifier> class <name>Builder</name> <super><extends>extends
        <name><name>com</name><operator>.</operator><name>google</name><operator>.</operator><name>protobuf</name><operator>.</operator><name>GeneratedMessage</name><operator>.</operator><name><name>Builder</name><argument_list type="generic">&lt;<argument><name>Builder</name></argument>&gt;</argument_list></name></name></extends>
       <implements>implements <name><name>org</name><operator>.</operator><name>thoughtcrime</name><operator>.</operator><name>securesms</name><operator>.</operator><name>devicelist</name><operator>.</operator><name>DeviceNameProtos</name><operator>.</operator><name>DeviceNameOrBuilder</name></name></implements></super> <block>{
      <function><specifier>public</specifier> <specifier>static</specifier> <specifier>final</specifier> <type><name><name>com</name><operator>.</operator><name>google</name><operator>.</operator><name>protobuf</name><operator>.</operator><name>Descriptors</name><operator>.</operator><name>Descriptor</name></name></type>
          <name>getDescriptor</name><parameter_list>()</parameter_list> <block>{
        <return>return <expr><name><name>org</name><operator>.</operator><name>thoughtcrime</name><operator>.</operator><name>securesms</name><operator>.</operator><name>devicelist</name><operator>.</operator><name>DeviceNameProtos</name><operator>.</operator><name>internal_static_signalservice_DeviceName_descriptor</name></name></expr>;</return>
      }</block></function>

      <function><specifier>protected</specifier> <type><name><name>com</name><operator>.</operator><name>google</name><operator>.</operator><name>protobuf</name><operator>.</operator><name>GeneratedMessage</name><operator>.</operator><name>FieldAccessorTable</name></name></type>
          <name>internalGetFieldAccessorTable</name><parameter_list>()</parameter_list> <block>{
        <return>return <expr><call><name><name>org</name><operator>.</operator><name>thoughtcrime</name><operator>.</operator><name>securesms</name><operator>.</operator><name>devicelist</name><operator>.</operator><name>DeviceNameProtos</name><operator>.</operator><name>internal_static_signalservice_DeviceName_fieldAccessorTable</name>
            <operator>.</operator><name>ensureFieldAccessorsInitialized</name></name><argument_list>(
                <argument><expr><name><name>org</name><operator>.</operator><name>thoughtcrime</name><operator>.</operator><name>securesms</name><operator>.</operator><name>devicelist</name><operator>.</operator><name>DeviceNameProtos</name><operator>.</operator><name>DeviceName</name><operator>.</operator><name>class</name></name></expr></argument>, <argument><expr><name><name>org</name><operator>.</operator><name>thoughtcrime</name><operator>.</operator><name>securesms</name><operator>.</operator><name>devicelist</name><operator>.</operator><name>DeviceNameProtos</name><operator>.</operator><name>DeviceName</name><operator>.</operator><name>Builder</name><operator>.</operator><name>class</name></name></expr></argument>)</argument_list></call></expr>;</return>
      }</block></function>

      <comment type="line">// Construct using org.thoughtcrime.securesms.devicelist.DeviceNameProtos.DeviceName.newBuilder()</comment>
      <constructor><specifier>private</specifier> <name>Builder</name><parameter_list>()</parameter_list> <block>{
        <expr_stmt><expr><call><name>maybeForceBuilderInitialization</name><argument_list>()</argument_list></call></expr>;</expr_stmt>
      }</block></constructor>

      <constructor><specifier>private</specifier> <name>Builder</name><parameter_list>(
          <parameter><decl><type><name><name>com</name><operator>.</operator><name>google</name><operator>.</operator><name>protobuf</name><operator>.</operator><name>GeneratedMessage</name><operator>.</operator><name>BuilderParent</name></name></type> <name>parent</name></decl></parameter>)</parameter_list> <block>{
        <expr_stmt><expr><call><name>super</name><argument_list>(<argument><expr><name>parent</name></expr></argument>)</argument_list></call></expr>;</expr_stmt>
        <expr_stmt><expr><call><name>maybeForceBuilderInitialization</name><argument_list>()</argument_list></call></expr>;</expr_stmt>
      }</block></constructor>
      <function><specifier>private</specifier> <type><name>void</name></type> <name>maybeForceBuilderInitialization</name><parameter_list>()</parameter_list> <block>{
        <if>if <condition>(<expr><name><name>com</name><operator>.</operator><name>google</name><operator>.</operator><name>protobuf</name><operator>.</operator><name>GeneratedMessage</name><operator>.</operator><name>alwaysUseFieldBuilders</name></name></expr>)</condition><then> <block>{
        }</block></then></if>
      }</block></function>
      <function><specifier>private</specifier> <specifier>static</specifier> <type><name>Builder</name></type> <name>create</name><parameter_list>()</parameter_list> <block>{
        <return>return <expr><operator>new</operator> <call><name>Builder</name><argument_list>()</argument_list></call></expr>;</return>
      }</block></function>

      <function><specifier>public</specifier> <type><name>Builder</name></type> <name>clear</name><parameter_list>()</parameter_list> <block>{
        <expr_stmt><expr><call><name><name>super</name><operator>.</operator><name>clear</name></name><argument_list>()</argument_list></call></expr>;</expr_stmt>
        <expr_stmt><expr><name>ephemeralPublic_</name> <operator>=</operator> <name><name>com</name><operator>.</operator><name>google</name><operator>.</operator><name>protobuf</name><operator>.</operator><name>ByteString</name><operator>.</operator><name>EMPTY</name></name></expr>;</expr_stmt>
        <expr_stmt><expr><name>bitField0_</name> <operator>=</operator> <operator>(</operator><name>bitField0_</name> <operator>&amp;</operator> <operator>~</operator><literal type="number">0x00000001</literal><operator>)</operator></expr>;</expr_stmt>
        <expr_stmt><expr><name>syntheticIv_</name> <operator>=</operator> <name><name>com</name><operator>.</operator><name>google</name><operator>.</operator><name>protobuf</name><operator>.</operator><name>ByteString</name><operator>.</operator><name>EMPTY</name></name></expr>;</expr_stmt>
        <expr_stmt><expr><name>bitField0_</name> <operator>=</operator> <operator>(</operator><name>bitField0_</name> <operator>&amp;</operator> <operator>~</operator><literal type="number">0x00000002</literal><operator>)</operator></expr>;</expr_stmt>
        <expr_stmt><expr><name>ciphertext_</name> <operator>=</operator> <name><name>com</name><operator>.</operator><name>google</name><operator>.</operator><name>protobuf</name><operator>.</operator><name>ByteString</name><operator>.</operator><name>EMPTY</name></name></expr>;</expr_stmt>
        <expr_stmt><expr><name>bitField0_</name> <operator>=</operator> <operator>(</operator><name>bitField0_</name> <operator>&amp;</operator> <operator>~</operator><literal type="number">0x00000004</literal><operator>)</operator></expr>;</expr_stmt>
        <return>return <expr><name>this</name></expr>;</return>
      }</block></function>

      <function><specifier>public</specifier> <type><name>Builder</name></type> <name>clone</name><parameter_list>()</parameter_list> <block>{
        <return>return <expr><call><name>create</name><argument_list>()</argument_list></call><operator>.</operator><call><name>mergeFrom</name><argument_list>(<argument><expr><call><name>buildPartial</name><argument_list>()</argument_list></call></expr></argument>)</argument_list></call></expr>;</return>
      }</block></function>

      <function><specifier>public</specifier> <type><name><name>com</name><operator>.</operator><name>google</name><operator>.</operator><name>protobuf</name><operator>.</operator><name>Descriptors</name><operator>.</operator><name>Descriptor</name></name></type>
          <name>getDescriptorForType</name><parameter_list>()</parameter_list> <block>{
        <return>return <expr><name><name>org</name><operator>.</operator><name>thoughtcrime</name><operator>.</operator><name>securesms</name><operator>.</operator><name>devicelist</name><operator>.</operator><name>DeviceNameProtos</name><operator>.</operator><name>internal_static_signalservice_DeviceName_descriptor</name></name></expr>;</return>
      }</block></function>

      <function><specifier>public</specifier> <type><name><name>org</name><operator>.</operator><name>thoughtcrime</name><operator>.</operator><name>securesms</name><operator>.</operator><name>devicelist</name><operator>.</operator><name>DeviceNameProtos</name><operator>.</operator><name>DeviceName</name></name></type> <name>getDefaultInstanceForType</name><parameter_list>()</parameter_list> <block>{
        <return>return <expr><call><name><name>org</name><operator>.</operator><name>thoughtcrime</name><operator>.</operator><name>securesms</name><operator>.</operator><name>devicelist</name><operator>.</operator><name>DeviceNameProtos</name><operator>.</operator><name>DeviceName</name><operator>.</operator><name>getDefaultInstance</name></name><argument_list>()</argument_list></call></expr>;</return>
      }</block></function>

      <function><specifier>public</specifier> <type><name><name>org</name><operator>.</operator><name>thoughtcrime</name><operator>.</operator><name>securesms</name><operator>.</operator><name>devicelist</name><operator>.</operator><name>DeviceNameProtos</name><operator>.</operator><name>DeviceName</name></name></type> <name>build</name><parameter_list>()</parameter_list> <block>{
        <decl_stmt><decl><type><name><name>org</name><operator>.</operator><name>thoughtcrime</name><operator>.</operator><name>securesms</name><operator>.</operator><name>devicelist</name><operator>.</operator><name>DeviceNameProtos</name><operator>.</operator><name>DeviceName</name></name></type> <name>result</name> <init>= <expr><call><name>buildPartial</name><argument_list>()</argument_list></call></expr></init></decl>;</decl_stmt>
        <if>if <condition>(<expr><operator>!</operator><call><name><name>result</name><operator>.</operator><name>isInitialized</name></name><argument_list>()</argument_list></call></expr>)</condition><then> <block>{
          <throw>throw <expr><call><name>newUninitializedMessageException</name><argument_list>(<argument><expr><name>result</name></expr></argument>)</argument_list></call></expr>;</throw>
        }</block></then></if>
        <return>return <expr><name>result</name></expr>;</return>
      }</block></function>

      <function><specifier>public</specifier> <type><name><name>org</name><operator>.</operator><name>thoughtcrime</name><operator>.</operator><name>securesms</name><operator>.</operator><name>devicelist</name><operator>.</operator><name>DeviceNameProtos</name><operator>.</operator><name>DeviceName</name></name></type> <name>buildPartial</name><parameter_list>()</parameter_list> <block>{
        <decl_stmt><decl><type><name><name>org</name><operator>.</operator><name>thoughtcrime</name><operator>.</operator><name>securesms</name><operator>.</operator><name>devicelist</name><operator>.</operator><name>DeviceNameProtos</name><operator>.</operator><name>DeviceName</name></name></type> <name>result</name> <init>= <expr><operator>new</operator> <call><name><name>org</name><operator>.</operator><name>thoughtcrime</name><operator>.</operator><name>securesms</name><operator>.</operator><name>devicelist</name><operator>.</operator><name>DeviceNameProtos</name><operator>.</operator><name>DeviceName</name></name><argument_list>(<argument><expr><name>this</name></expr></argument>)</argument_list></call></expr></init></decl>;</decl_stmt>
        <decl_stmt><decl><type><name>int</name></type> <name>from_bitField0_</name> <init>= <expr><name>bitField0_</name></expr></init></decl>;</decl_stmt>
        <decl_stmt><decl><type><name>int</name></type> <name>to_bitField0_</name> <init>= <expr><literal type="number">0</literal></expr></init></decl>;</decl_stmt>
        <if>if <condition>(<expr><operator>(</operator><operator>(</operator><name>from_bitField0_</name> <operator>&amp;</operator> <literal type="number">0x00000001</literal><operator>)</operator> <operator>==</operator> <literal type="number">0x00000001</literal><operator>)</operator></expr>)</condition><then> <block>{
          <expr_stmt><expr><name>to_bitField0_</name> <operator>|=</operator> <literal type="number">0x00000001</literal></expr>;</expr_stmt>
        }</block></then></if>
        <expr_stmt><expr><name><name>result</name><operator>.</operator><name>ephemeralPublic_</name></name> <operator>=</operator> <name>ephemeralPublic_</name></expr>;</expr_stmt>
        <if>if <condition>(<expr><operator>(</operator><operator>(</operator><name>from_bitField0_</name> <operator>&amp;</operator> <literal type="number">0x00000002</literal><operator>)</operator> <operator>==</operator> <literal type="number">0x00000002</literal><operator>)</operator></expr>)</condition><then> <block>{
          <expr_stmt><expr><name>to_bitField0_</name> <operator>|=</operator> <literal type="number">0x00000002</literal></expr>;</expr_stmt>
        }</block></then></if>
        <expr_stmt><expr><name><name>result</name><operator>.</operator><name>syntheticIv_</name></name> <operator>=</operator> <name>syntheticIv_</name></expr>;</expr_stmt>
        <if>if <condition>(<expr><operator>(</operator><operator>(</operator><name>from_bitField0_</name> <operator>&amp;</operator> <literal type="number">0x00000004</literal><operator>)</operator> <operator>==</operator> <literal type="number">0x00000004</literal><operator>)</operator></expr>)</condition><then> <block>{
          <expr_stmt><expr><name>to_bitField0_</name> <operator>|=</operator> <literal type="number">0x00000004</literal></expr>;</expr_stmt>
        }</block></then></if>
        <expr_stmt><expr><name><name>result</name><operator>.</operator><name>ciphertext_</name></name> <operator>=</operator> <name>ciphertext_</name></expr>;</expr_stmt>
        <expr_stmt><expr><name><name>result</name><operator>.</operator><name>bitField0_</name></name> <operator>=</operator> <name>to_bitField0_</name></expr>;</expr_stmt>
        <expr_stmt><expr><call><name>onBuilt</name><argument_list>()</argument_list></call></expr>;</expr_stmt>
        <return>return <expr><name>result</name></expr>;</return>
      }</block></function>

      <function><specifier>public</specifier> <type><name>Builder</name></type> <name>mergeFrom</name><parameter_list>(<parameter><decl><type><name><name>com</name><operator>.</operator><name>google</name><operator>.</operator><name>protobuf</name><operator>.</operator><name>Message</name></name></type> <name>other</name></decl></parameter>)</parameter_list> <block>{
        <if>if <condition>(<expr><name>other</name> <operator>instanceof</operator> <name><name>org</name><operator>.</operator><name>thoughtcrime</name><operator>.</operator><name>securesms</name><operator>.</operator><name>devicelist</name><operator>.</operator><name>DeviceNameProtos</name><operator>.</operator><name>DeviceName</name></name></expr>)</condition><then> <block>{
          <return>return <expr><call><name>mergeFrom</name><argument_list>(<argument><expr><operator>(</operator><name><name>org</name><operator>.</operator><name>thoughtcrime</name><operator>.</operator><name>securesms</name><operator>.</operator><name>devicelist</name><operator>.</operator><name>DeviceNameProtos</name><operator>.</operator><name>DeviceName</name></name><operator>)</operator><name>other</name></expr></argument>)</argument_list></call></expr>;</return>
        }</block></then> <else>else <block>{
          <expr_stmt><expr><call><name><name>super</name><operator>.</operator><name>mergeFrom</name></name><argument_list>(<argument><expr><name>other</name></expr></argument>)</argument_list></call></expr>;</expr_stmt>
          <return>return <expr><name>this</name></expr>;</return>
        }</block></else></if>
      }</block></function>

      <function><specifier>public</specifier> <type><name>Builder</name></type> <name>mergeFrom</name><parameter_list>(<parameter><decl><type><name><name>org</name><operator>.</operator><name>thoughtcrime</name><operator>.</operator><name>securesms</name><operator>.</operator><name>devicelist</name><operator>.</operator><name>DeviceNameProtos</name><operator>.</operator><name>DeviceName</name></name></type> <name>other</name></decl></parameter>)</parameter_list> <block>{
        <if>if <condition>(<expr><name>other</name> <operator>==</operator> <call><name><name>org</name><operator>.</operator><name>thoughtcrime</name><operator>.</operator><name>securesms</name><operator>.</operator><name>devicelist</name><operator>.</operator><name>DeviceNameProtos</name><operator>.</operator><name>DeviceName</name><operator>.</operator><name>getDefaultInstance</name></name><argument_list>()</argument_list></call></expr>)</condition><then> <block type="pseudo"><return>return <expr><name>this</name></expr>;</return></block></then></if>
        <if>if <condition>(<expr><call><name><name>other</name><operator>.</operator><name>hasEphemeralPublic</name></name><argument_list>()</argument_list></call></expr>)</condition><then> <block>{
          <expr_stmt><expr><call><name>setEphemeralPublic</name><argument_list>(<argument><expr><call><name><name>other</name><operator>.</operator><name>getEphemeralPublic</name></name><argument_list>()</argument_list></call></expr></argument>)</argument_list></call></expr>;</expr_stmt>
        }</block></then></if>
        <if>if <condition>(<expr><call><name><name>other</name><operator>.</operator><name>hasSyntheticIv</name></name><argument_list>()</argument_list></call></expr>)</condition><then> <block>{
          <expr_stmt><expr><call><name>setSyntheticIv</name><argument_list>(<argument><expr><call><name><name>other</name><operator>.</operator><name>getSyntheticIv</name></name><argument_list>()</argument_list></call></expr></argument>)</argument_list></call></expr>;</expr_stmt>
        }</block></then></if>
        <if>if <condition>(<expr><call><name><name>other</name><operator>.</operator><name>hasCiphertext</name></name><argument_list>()</argument_list></call></expr>)</condition><then> <block>{
          <expr_stmt><expr><call><name>setCiphertext</name><argument_list>(<argument><expr><call><name><name>other</name><operator>.</operator><name>getCiphertext</name></name><argument_list>()</argument_list></call></expr></argument>)</argument_list></call></expr>;</expr_stmt>
        }</block></then></if>
        <expr_stmt><expr><call><name><name>this</name><operator>.</operator><name>mergeUnknownFields</name></name><argument_list>(<argument><expr><call><name><name>other</name><operator>.</operator><name>getUnknownFields</name></name><argument_list>()</argument_list></call></expr></argument>)</argument_list></call></expr>;</expr_stmt>
        <return>return <expr><name>this</name></expr>;</return>
      }</block></function>

      <function><specifier>public</specifier> <specifier>final</specifier> <type><name>boolean</name></type> <name>isInitialized</name><parameter_list>()</parameter_list> <block>{
        <return>return <expr><literal type="boolean">true</literal></expr>;</return>
      }</block></function>

      <function><specifier>public</specifier> <type><name>Builder</name></type> <name>mergeFrom</name><parameter_list>(
          <parameter><decl><type><name><name>com</name><operator>.</operator><name>google</name><operator>.</operator><name>protobuf</name><operator>.</operator><name>CodedInputStream</name></name></type> <name>input</name></decl></parameter>,
          <parameter><decl><type><name><name>com</name><operator>.</operator><name>google</name><operator>.</operator><name>protobuf</name><operator>.</operator><name>ExtensionRegistryLite</name></name></type> <name>extensionRegistry</name></decl></parameter>)</parameter_list>
          <throws>throws <argument><expr><name><name>java</name><operator>.</operator><name>io</name><operator>.</operator><name>IOException</name></name></expr></argument></throws> <block>{
        <decl_stmt><decl><type><name><name>org</name><operator>.</operator><name>thoughtcrime</name><operator>.</operator><name>securesms</name><operator>.</operator><name>devicelist</name><operator>.</operator><name>DeviceNameProtos</name><operator>.</operator><name>DeviceName</name></name></type> <name>parsedMessage</name> <init>= <expr><literal type="null">null</literal></expr></init></decl>;</decl_stmt>
        <try>try <block>{
          <expr_stmt><expr><name>parsedMessage</name> <operator>=</operator> <call><name><name>PARSER</name><operator>.</operator><name>parsePartialFrom</name></name><argument_list>(<argument><expr><name>input</name></expr></argument>, <argument><expr><name>extensionRegistry</name></expr></argument>)</argument_list></call></expr>;</expr_stmt>
        }</block> <catch>catch <parameter_list>(<parameter><decl><type><name><name>com</name><operator>.</operator><name>google</name><operator>.</operator><name>protobuf</name><operator>.</operator><name>InvalidProtocolBufferException</name></name></type> <name>e</name></decl></parameter>)</parameter_list> <block>{
          <expr_stmt><expr><name>parsedMessage</name> <operator>=</operator> <operator>(</operator><name><name>org</name><operator>.</operator><name>thoughtcrime</name><operator>.</operator><name>securesms</name><operator>.</operator><name>devicelist</name><operator>.</operator><name>DeviceNameProtos</name><operator>.</operator><name>DeviceName</name></name><operator>)</operator> <call><name><name>e</name><operator>.</operator><name>getUnfinishedMessage</name></name><argument_list>()</argument_list></call></expr>;</expr_stmt>
          <throw>throw <expr><name>e</name></expr>;</throw>
        }</block></catch> <finally>finally <block>{
          <if>if <condition>(<expr><name>parsedMessage</name> <operator>!=</operator> <literal type="null">null</literal></expr>)</condition><then> <block>{
            <expr_stmt><expr><call><name>mergeFrom</name><argument_list>(<argument><expr><name>parsedMessage</name></expr></argument>)</argument_list></call></expr>;</expr_stmt>
          }</block></then></if>
        }</block></finally></try>
        <return>return <expr><name>this</name></expr>;</return>
      }</block></function>
      <decl_stmt><decl><specifier>private</specifier> <type><name>int</name></type> <name>bitField0_</name></decl>;</decl_stmt>

      <comment type="line">// optional bytes ephemeralPublic = 1;</comment>
      <decl_stmt><decl><specifier>private</specifier> <type><name><name>com</name><operator>.</operator><name>google</name><operator>.</operator><name>protobuf</name><operator>.</operator><name>ByteString</name></name></type> <name>ephemeralPublic_</name> <init>= <expr><name><name>com</name><operator>.</operator><name>google</name><operator>.</operator><name>protobuf</name><operator>.</operator><name>ByteString</name><operator>.</operator><name>EMPTY</name></name></expr></init></decl>;</decl_stmt>
      <comment type="block" format="javadoc">/**
       * &lt;code&gt;optional bytes ephemeralPublic = 1;&lt;/code&gt;
       */</comment>
      <function><specifier>public</specifier> <type><name>boolean</name></type> <name>hasEphemeralPublic</name><parameter_list>()</parameter_list> <block>{
        <return>return <expr><operator>(</operator><operator>(</operator><name>bitField0_</name> <operator>&amp;</operator> <literal type="number">0x00000001</literal><operator>)</operator> <operator>==</operator> <literal type="number">0x00000001</literal><operator>)</operator></expr>;</return>
      }</block></function>
      <comment type="block" format="javadoc">/**
       * &lt;code&gt;optional bytes ephemeralPublic = 1;&lt;/code&gt;
       */</comment>
      <function><specifier>public</specifier> <type><name><name>com</name><operator>.</operator><name>google</name><operator>.</operator><name>protobuf</name><operator>.</operator><name>ByteString</name></name></type> <name>getEphemeralPublic</name><parameter_list>()</parameter_list> <block>{
        <return>return <expr><name>ephemeralPublic_</name></expr>;</return>
      }</block></function>
      <comment type="block" format="javadoc">/**
       * &lt;code&gt;optional bytes ephemeralPublic = 1;&lt;/code&gt;
       */</comment>
      <function><specifier>public</specifier> <type><name>Builder</name></type> <name>setEphemeralPublic</name><parameter_list>(<parameter><decl><type><name><name>com</name><operator>.</operator><name>google</name><operator>.</operator><name>protobuf</name><operator>.</operator><name>ByteString</name></name></type> <name>value</name></decl></parameter>)</parameter_list> <block>{
        <if>if <condition>(<expr><name>value</name> <operator>==</operator> <literal type="null">null</literal></expr>)</condition><then> <block>{
    <throw>throw <expr><operator>new</operator> <call><name>NullPointerException</name><argument_list>()</argument_list></call></expr>;</throw>
  }</block></then></if>
  <expr_stmt><expr><name>bitField0_</name> <operator>|=</operator> <literal type="number">0x00000001</literal></expr>;</expr_stmt>
        <expr_stmt><expr><name>ephemeralPublic_</name> <operator>=</operator> <name>value</name></expr>;</expr_stmt>
        <expr_stmt><expr><call><name>onChanged</name><argument_list>()</argument_list></call></expr>;</expr_stmt>
        <return>return <expr><name>this</name></expr>;</return>
      }</block></function>
      <comment type="block" format="javadoc">/**
       * &lt;code&gt;optional bytes ephemeralPublic = 1;&lt;/code&gt;
       */</comment>
      <function><specifier>public</specifier> <type><name>Builder</name></type> <name>clearEphemeralPublic</name><parameter_list>()</parameter_list> <block>{
        <expr_stmt><expr><name>bitField0_</name> <operator>=</operator> <operator>(</operator><name>bitField0_</name> <operator>&amp;</operator> <operator>~</operator><literal type="number">0x00000001</literal><operator>)</operator></expr>;</expr_stmt>
        <expr_stmt><expr><name>ephemeralPublic_</name> <operator>=</operator> <call><name>getDefaultInstance</name><argument_list>()</argument_list></call><operator>.</operator><call><name>getEphemeralPublic</name><argument_list>()</argument_list></call></expr>;</expr_stmt>
        <expr_stmt><expr><call><name>onChanged</name><argument_list>()</argument_list></call></expr>;</expr_stmt>
        <return>return <expr><name>this</name></expr>;</return>
      }</block></function>

      <comment type="line">// optional bytes syntheticIv = 2;</comment>
      <decl_stmt><decl><specifier>private</specifier> <type><name><name>com</name><operator>.</operator><name>google</name><operator>.</operator><name>protobuf</name><operator>.</operator><name>ByteString</name></name></type> <name>syntheticIv_</name> <init>= <expr><name><name>com</name><operator>.</operator><name>google</name><operator>.</operator><name>protobuf</name><operator>.</operator><name>ByteString</name><operator>.</operator><name>EMPTY</name></name></expr></init></decl>;</decl_stmt>
      <comment type="block" format="javadoc">/**
       * &lt;code&gt;optional bytes syntheticIv = 2;&lt;/code&gt;
       */</comment>
      <function><specifier>public</specifier> <type><name>boolean</name></type> <name>hasSyntheticIv</name><parameter_list>()</parameter_list> <block>{
        <return>return <expr><operator>(</operator><operator>(</operator><name>bitField0_</name> <operator>&amp;</operator> <literal type="number">0x00000002</literal><operator>)</operator> <operator>==</operator> <literal type="number">0x00000002</literal><operator>)</operator></expr>;</return>
      }</block></function>
      <comment type="block" format="javadoc">/**
       * &lt;code&gt;optional bytes syntheticIv = 2;&lt;/code&gt;
       */</comment>
      <function><specifier>public</specifier> <type><name><name>com</name><operator>.</operator><name>google</name><operator>.</operator><name>protobuf</name><operator>.</operator><name>ByteString</name></name></type> <name>getSyntheticIv</name><parameter_list>()</parameter_list> <block>{
        <return>return <expr><name>syntheticIv_</name></expr>;</return>
      }</block></function>
      <comment type="block" format="javadoc">/**
       * &lt;code&gt;optional bytes syntheticIv = 2;&lt;/code&gt;
       */</comment>
      <function><specifier>public</specifier> <type><name>Builder</name></type> <name>setSyntheticIv</name><parameter_list>(<parameter><decl><type><name><name>com</name><operator>.</operator><name>google</name><operator>.</operator><name>protobuf</name><operator>.</operator><name>ByteString</name></name></type> <name>value</name></decl></parameter>)</parameter_list> <block>{
        <if>if <condition>(<expr><name>value</name> <operator>==</operator> <literal type="null">null</literal></expr>)</condition><then> <block>{
    <throw>throw <expr><operator>new</operator> <call><name>NullPointerException</name><argument_list>()</argument_list></call></expr>;</throw>
  }</block></then></if>
  <expr_stmt><expr><name>bitField0_</name> <operator>|=</operator> <literal type="number">0x00000002</literal></expr>;</expr_stmt>
        <expr_stmt><expr><name>syntheticIv_</name> <operator>=</operator> <name>value</name></expr>;</expr_stmt>
        <expr_stmt><expr><call><name>onChanged</name><argument_list>()</argument_list></call></expr>;</expr_stmt>
        <return>return <expr><name>this</name></expr>;</return>
      }</block></function>
      <comment type="block" format="javadoc">/**
       * &lt;code&gt;optional bytes syntheticIv = 2;&lt;/code&gt;
       */</comment>
      <function><specifier>public</specifier> <type><name>Builder</name></type> <name>clearSyntheticIv</name><parameter_list>()</parameter_list> <block>{
        <expr_stmt><expr><name>bitField0_</name> <operator>=</operator> <operator>(</operator><name>bitField0_</name> <operator>&amp;</operator> <operator>~</operator><literal type="number">0x00000002</literal><operator>)</operator></expr>;</expr_stmt>
        <expr_stmt><expr><name>syntheticIv_</name> <operator>=</operator> <call><name>getDefaultInstance</name><argument_list>()</argument_list></call><operator>.</operator><call><name>getSyntheticIv</name><argument_list>()</argument_list></call></expr>;</expr_stmt>
        <expr_stmt><expr><call><name>onChanged</name><argument_list>()</argument_list></call></expr>;</expr_stmt>
        <return>return <expr><name>this</name></expr>;</return>
      }</block></function>

      <comment type="line">// optional bytes ciphertext = 3;</comment>
      <decl_stmt><decl><specifier>private</specifier> <type><name><name>com</name><operator>.</operator><name>google</name><operator>.</operator><name>protobuf</name><operator>.</operator><name>ByteString</name></name></type> <name>ciphertext_</name> <init>= <expr><name><name>com</name><operator>.</operator><name>google</name><operator>.</operator><name>protobuf</name><operator>.</operator><name>ByteString</name><operator>.</operator><name>EMPTY</name></name></expr></init></decl>;</decl_stmt>
      <comment type="block" format="javadoc">/**
       * &lt;code&gt;optional bytes ciphertext = 3;&lt;/code&gt;
       */</comment>
      <function><specifier>public</specifier> <type><name>boolean</name></type> <name>hasCiphertext</name><parameter_list>()</parameter_list> <block>{
        <return>return <expr><operator>(</operator><operator>(</operator><name>bitField0_</name> <operator>&amp;</operator> <literal type="number">0x00000004</literal><operator>)</operator> <operator>==</operator> <literal type="number">0x00000004</literal><operator>)</operator></expr>;</return>
      }</block></function>
      <comment type="block" format="javadoc">/**
       * &lt;code&gt;optional bytes ciphertext = 3;&lt;/code&gt;
       */</comment>
      <function><specifier>public</specifier> <type><name><name>com</name><operator>.</operator><name>google</name><operator>.</operator><name>protobuf</name><operator>.</operator><name>ByteString</name></name></type> <name>getCiphertext</name><parameter_list>()</parameter_list> <block>{
        <return>return <expr><name>ciphertext_</name></expr>;</return>
      }</block></function>
      <comment type="block" format="javadoc">/**
       * &lt;code&gt;optional bytes ciphertext = 3;&lt;/code&gt;
       */</comment>
      <function><specifier>public</specifier> <type><name>Builder</name></type> <name>setCiphertext</name><parameter_list>(<parameter><decl><type><name><name>com</name><operator>.</operator><name>google</name><operator>.</operator><name>protobuf</name><operator>.</operator><name>ByteString</name></name></type> <name>value</name></decl></parameter>)</parameter_list> <block>{
        <if>if <condition>(<expr><name>value</name> <operator>==</operator> <literal type="null">null</literal></expr>)</condition><then> <block>{
    <throw>throw <expr><operator>new</operator> <call><name>NullPointerException</name><argument_list>()</argument_list></call></expr>;</throw>
  }</block></then></if>
  <expr_stmt><expr><name>bitField0_</name> <operator>|=</operator> <literal type="number">0x00000004</literal></expr>;</expr_stmt>
        <expr_stmt><expr><name>ciphertext_</name> <operator>=</operator> <name>value</name></expr>;</expr_stmt>
        <expr_stmt><expr><call><name>onChanged</name><argument_list>()</argument_list></call></expr>;</expr_stmt>
        <return>return <expr><name>this</name></expr>;</return>
      }</block></function>
      <comment type="block" format="javadoc">/**
       * &lt;code&gt;optional bytes ciphertext = 3;&lt;/code&gt;
       */</comment>
      <function><specifier>public</specifier> <type><name>Builder</name></type> <name>clearCiphertext</name><parameter_list>()</parameter_list> <block>{
        <expr_stmt><expr><name>bitField0_</name> <operator>=</operator> <operator>(</operator><name>bitField0_</name> <operator>&amp;</operator> <operator>~</operator><literal type="number">0x00000004</literal><operator>)</operator></expr>;</expr_stmt>
        <expr_stmt><expr><name>ciphertext_</name> <operator>=</operator> <call><name>getDefaultInstance</name><argument_list>()</argument_list></call><operator>.</operator><call><name>getCiphertext</name><argument_list>()</argument_list></call></expr>;</expr_stmt>
        <expr_stmt><expr><call><name>onChanged</name><argument_list>()</argument_list></call></expr>;</expr_stmt>
        <return>return <expr><name>this</name></expr>;</return>
      }</block></function>

      <comment type="line">// @@protoc_insertion_point(builder_scope:signalservice.DeviceName)</comment>
    }</block></class>

    <static>static <block>{
      <expr_stmt><expr><name>defaultInstance</name> <operator>=</operator> <operator>new</operator> <call><name>DeviceName</name><argument_list>(<argument><expr><literal type="boolean">true</literal></expr></argument>)</argument_list></call></expr>;</expr_stmt>
      <expr_stmt><expr><call><name><name>defaultInstance</name><operator>.</operator><name>initFields</name></name><argument_list>()</argument_list></call></expr>;</expr_stmt>
    }</block></static>

    <comment type="line">// @@protoc_insertion_point(class_scope:signalservice.DeviceName)</comment>
  }</block></class>

  <decl_stmt><decl><specifier>private</specifier> <specifier>static</specifier> <type><name><name>com</name><operator>.</operator><name>google</name><operator>.</operator><name>protobuf</name><operator>.</operator><name>Descriptors</name><operator>.</operator><name>Descriptor</name></name></type>
    <name>internal_static_signalservice_DeviceName_descriptor</name></decl>;</decl_stmt>
  <decl_stmt><decl><specifier>private</specifier> <specifier>static</specifier>
    <type><name><name>com</name><operator>.</operator><name>google</name><operator>.</operator><name>protobuf</name><operator>.</operator><name>GeneratedMessage</name><operator>.</operator><name>FieldAccessorTable</name></name></type>
      <name>internal_static_signalservice_DeviceName_fieldAccessorTable</name></decl>;</decl_stmt>

  <function><specifier>public</specifier> <specifier>static</specifier> <type><name><name>com</name><operator>.</operator><name>google</name><operator>.</operator><name>protobuf</name><operator>.</operator><name>Descriptors</name><operator>.</operator><name>FileDescriptor</name></name></type>
      <name>getDescriptor</name><parameter_list>()</parameter_list> <block>{
    <return>return <expr><name>descriptor</name></expr>;</return>
  }</block></function>
  <decl_stmt><decl><specifier>private</specifier> <specifier>static</specifier> <type><name><name>com</name><operator>.</operator><name>google</name><operator>.</operator><name>protobuf</name><operator>.</operator><name>Descriptors</name><operator>.</operator><name>FileDescriptor</name></name></type>
      <name>descriptor</name></decl>;</decl_stmt>
  <static>static <block>{
    <decl_stmt><decl><type><name><name>java</name><operator>.</operator><name>lang</name><operator>.</operator><name>String</name><index>[]</index></name></type> <name>descriptorData</name> <init>= <expr><block>{
      <expr><literal type="string">"\n\020DeviceName.proto\022\rsignalservice\"N\n\nDev"</literal> <operator>+</operator>
      <literal type="string">"iceName\022\027\n\017ephemeralPublic\030\001 \001(\014\022\023\n\013synt"</literal> <operator>+</operator>
      <literal type="string">"heticIv\030\002 \001(\014\022\022\n\nciphertext\030\003 \001(\014B9\n%org"</literal> <operator>+</operator>
      <literal type="string">".thoughtcrime.securesms.devicelistB\020Devi"</literal> <operator>+</operator>
      <literal type="string">"ceNameProtos"</literal></expr>
    }</block></expr></init></decl>;</decl_stmt>
    <decl_stmt><decl><type><name><name>com</name><operator>.</operator><name>google</name><operator>.</operator><name>protobuf</name><operator>.</operator><name>Descriptors</name><operator>.</operator><name>FileDescriptor</name><operator>.</operator><name>InternalDescriptorAssigner</name></name></type> <name>assigner</name> <init>=
      <expr><operator>new</operator> <class><super><name><name>com</name><operator>.</operator><name>google</name><operator>.</operator><name>protobuf</name><operator>.</operator><name>Descriptors</name><operator>.</operator><name>FileDescriptor</name><operator>.</operator><name>InternalDescriptorAssigner</name></name></super><argument_list>()</argument_list> <block>{
        <function><specifier>public</specifier> <type><name><name>com</name><operator>.</operator><name>google</name><operator>.</operator><name>protobuf</name><operator>.</operator><name>ExtensionRegistry</name></name></type> <name>assignDescriptors</name><parameter_list>(
            <parameter><decl><type><name><name>com</name><operator>.</operator><name>google</name><operator>.</operator><name>protobuf</name><operator>.</operator><name>Descriptors</name><operator>.</operator><name>FileDescriptor</name></name></type> <name>root</name></decl></parameter>)</parameter_list> <block>{
          <expr_stmt><expr><name>descriptor</name> <operator>=</operator> <name>root</name></expr>;</expr_stmt>
          <expr_stmt><expr><name>internal_static_signalservice_DeviceName_descriptor</name> <operator>=</operator>
            <call><name>getDescriptor</name><argument_list>()</argument_list></call><operator>.</operator><call><name>getMessageTypes</name><argument_list>()</argument_list></call><operator>.</operator><call><name>get</name><argument_list>(<argument><expr><literal type="number">0</literal></expr></argument>)</argument_list></call></expr>;</expr_stmt>
          <expr_stmt><expr><name>internal_static_signalservice_DeviceName_fieldAccessorTable</name> <operator>=</operator> <operator>new</operator>
            <call><name><name>com</name><operator>.</operator><name>google</name><operator>.</operator><name>protobuf</name><operator>.</operator><name>GeneratedMessage</name><operator>.</operator><name>FieldAccessorTable</name></name><argument_list>(
              <argument><expr><name>internal_static_signalservice_DeviceName_descriptor</name></expr></argument>,
              <argument><expr><operator>new</operator> <name><name>java</name><operator>.</operator><name>lang</name><operator>.</operator><name>String</name><index>[]</index></name> <block>{ <expr><literal type="string">"EphemeralPublic"</literal></expr>, <expr><literal type="string">"SyntheticIv"</literal></expr>, <expr><literal type="string">"Ciphertext"</literal></expr>, }</block></expr></argument>)</argument_list></call></expr>;</expr_stmt>
          <return>return <expr><literal type="null">null</literal></expr>;</return>
        }</block></function>
      }</block></class></expr></init></decl>;</decl_stmt>
    <expr_stmt><expr><call><name><name>com</name><operator>.</operator><name>google</name><operator>.</operator><name>protobuf</name><operator>.</operator><name>Descriptors</name><operator>.</operator><name>FileDescriptor</name>
      <operator>.</operator><name>internalBuildGeneratedFileFrom</name></name><argument_list>(<argument><expr><name>descriptorData</name></expr></argument>,
        <argument><expr><operator>new</operator> <name><name>com</name><operator>.</operator><name>google</name><operator>.</operator><name>protobuf</name><operator>.</operator><name>Descriptors</name><operator>.</operator><name>FileDescriptor</name><index>[]</index></name> <block>{
        }</block></expr></argument>, <argument><expr><name>assigner</name></expr></argument>)</argument_list></call></expr>;</expr_stmt>
  }</block></static>

  <comment type="line">// @@protoc_insertion_point(outer_class_scope)</comment>
}</block></class>
</unit>
