{"EstimationModel":"exucp_lm","SizeMetric":"EXUCP","TransactionMetric":"SWTII","Effort":"1.29","UseCases":[{"Name":"Attract charity enthusiasts and craft unthusiast","_id":"EAID_9827F44C_1C73_4d20_B04C_F9112CDF63EB","SizeMeasurement":"0.00","feasible":true,"Personnel_UI":"50.00%","Personnel_DB":"25.00%","Personnel_FS":"25.00%","Personnel":3,"Duration":"0.00","Effort":"0.00","useCasePMEffort":"-1.00","useCaseDEVEffort":"-1.00","synthesizedEffort":"0.00","BusinessValue":0,"BVEffortRatio":"0.00"},{"Name":"Customers","_id":"EAID_17525508_F53C_4ad3_B80D_A4C222C23291","SizeMeasurement":"0.00","feasible":true,"Personnel_UI":"50.00%","Personnel_DB":"25.00%","Personnel_FS":"25.00%","Personnel":3,"Duration":"0.00","Effort":"0.00","useCasePMEffort":"-1.00","useCaseDEVEffort":"-1.00","synthesizedEffort":"0.00","BusinessValue":0,"BVEffortRatio":"0.00"},{"Name":"Facebook","_id":"EAID_52163012_AF9E_429e_BE8A_BFDFE821DDE5","SizeMeasurement":"0.00","feasible":true,"Personnel_UI":"50.00%","Personnel_DB":"25.00%","Personnel_FS":"25.00%","Personnel":3,"Duration":"0.00","Effort":"0.00","useCasePMEffort":"-1.00","useCaseDEVEffort":"-1.00","synthesizedEffort":"0.00","BusinessValue":0,"BVEffortRatio":"0.00"},{"Name":"Increase awareness about the charity","_id":"EAID_1DCAD1C7_6426_40a9_9E29_A35F5639A0BB","SizeMeasurement":"0.00","feasible":true,"Personnel_UI":"50.00%","Personnel_DB":"25.00%","Personnel_FS":"25.00%","Personnel":3,"Duration":"0.00","Effort":"0.00","useCasePMEffort":"-1.00","useCaseDEVEffort":"-1.00","synthesizedEffort":"0.00","BusinessValue":0,"BVEffortRatio":"0.00"},{"Name":"Increase sales (Increase charitable donations)","_id":"EAID_E6FDF246_4086_4b97_9A66_4D8FC30A8F4E","SizeMeasurement":"0.00","feasible":true,"Personnel_UI":"50.00%","Personnel_DB":"25.00%","Personnel_FS":"25.00%","Personnel":3,"Duration":"0.00","Effort":"0.00","useCasePMEffort":"-1.00","useCaseDEVEffort":"-1.00","synthesizedEffort":"0.00","BusinessValue":0,"BVEffortRatio":"0.00"},{"Name":"Internet","_id":"EAID_A004EC78_2B35_4791_861F_FDB97064D070","SizeMeasurement":"0.00","feasible":true,"Personnel_UI":"50.00%","Personnel_DB":"25.00%","Personnel_FS":"25.00%","Personnel":3,"Duration":"0.00","Effort":"0.00","useCasePMEffort":"-1.00","useCaseDEVEffort":"-1.00","synthesizedEffort":"0.00","BusinessValue":0,"BVEffortRatio":"0.00"},{"Name":"Maintainer","_id":"EAID_B2E0C244_9EF9_4c6f_9FC5_B41E5BFA9AD1","SizeMeasurement":"0.00","feasible":true,"Personnel_UI":"50.00%","Personnel_DB":"25.00%","Personnel_FS":"25.00%","Personnel":3,"Duration":"0.00","Effort":"0.00","useCasePMEffort":"-1.00","useCaseDEVEffort":"-1.00","synthesizedEffort":"0.00","BusinessValue":0,"BVEffortRatio":"0.00"},{"Name":"Make the site easy to navigate and fun to use","_id":"EAID_8464E317_DCF7_4d36_9771_436E9E178559","SizeMeasurement":"0.00","feasible":true,"Personnel_UI":"50.00%","Personnel_DB":"25.00%","Personnel_FS":"25.00%","Personnel":3,"Duration":"0.00","Effort":"0.00","useCasePMEffort":"-1.00","useCaseDEVEffort":"-1.00","synthesizedEffort":"0.00","BusinessValue":0,"BVEffortRatio":"0.00"},{"Name":"Paypal","_id":"EAID_C9B54C02_755C_4531_B042_E56DEF84E3B2","SizeMeasurement":"0.00","feasible":true,"Personnel_UI":"50.00%","Personnel_DB":"25.00%","Personnel_FS":"25.00%","Personnel":3,"Duration":"0.00","Effort":"0.00","useCasePMEffort":"-1.00","useCaseDEVEffort":"-1.00","synthesizedEffort":"0.00","BusinessValue":0,"BVEffortRatio":"0.00"},{"Name":"Twitter","_id":"EAID_E3A32B37_3BC6_4c0f_9CD2_D090FB3C1AE0","SizeMeasurement":"0.00","feasible":true,"Personnel_UI":"50.00%","Personnel_DB":"25.00%","Personnel_FS":"25.00%","Personnel":3,"Duration":"0.00","Effort":"0.00","useCasePMEffort":"-1.00","useCaseDEVEffort":"-1.00","synthesizedEffort":"0.00","BusinessValue":0,"BVEffortRatio":"0.00"}],"DomainModel":{"MVCEstimates":{"ViewEffort":"0.00","ModelEffort":"0.00","ControlEffort":"0.00"}},"SizeMeasurement":"1.00","feasible":true,"Personnel":1,"Duration":"0.58","HoursPerMonth":152,"Personnel_UI":"50.00%","Personnel_DB":"25.00%","Personnel_FS":"25.00%","TotalSynthesizedEffort":0,"EstimationResultsFile":"estimationResultEXUCP.json"}