[
  {
    "column name": "id",
    "statistics": {
      "mean": 5.5,
      "variance": 9.1667,
      "first_quartile": 3.25,
      "median": 5.5,
      "third_quartile": 7.75,
      "kurtosis": -1.5616
    },
    "dist chart path": "C:\\Users\\flyqk\\Documents\\Research Projects\\UMLx\\data\\Resilient Agile\\s16b_bad_driver_2018-8-19@1537423576395_analysis/EAID_2CBE2BAF_7C5E_437c_942F_B0420A261BAE/id_distribution_chart.svg"
  },
  {
    "column name": "transaction_length",
    "statistics": {
      "mean": 4.5,
      "variance": 1.1667,
      "first_quartile": 4,
      "median": 4,
      "third_quartile": 5.5,
      "kurtosis": -1.4847
    },
    "dist chart path": "C:\\Users\\flyqk\\Documents\\Research Projects\\UMLx\\data\\Resilient Agile\\s16b_bad_driver_2018-8-19@1537423576395_analysis/EAID_2CBE2BAF_7C5E_437c_942F_B0420A261BAE/transaction_length_distribution_chart.svg"
  },
  {
    "column name": "boundry_num",
    "statistics": {
      "mean": 0.3,
      "variance": 0.2333,
      "first_quartile": 0,
      "median": 0,
      "third_quartile": 0.75,
      "kurtosis": -1.5729
    },
    "dist chart path": "C:\\Users\\flyqk\\Documents\\Research Projects\\UMLx\\data\\Resilient Agile\\s16b_bad_driver_2018-8-19@1537423576395_analysis/EAID_2CBE2BAF_7C5E_437c_942F_B0420A261BAE/boundry_num_distribution_chart.svg"
  },
  {
    "column name": "control_num",
    "statistics": {
      "mean": 2.5,
      "variance": 0.9444,
      "first_quartile": 2,
      "median": 2,
      "third_quartile": 3,
      "kurtosis": -1.2483
    },
    "dist chart path": "C:\\Users\\flyqk\\Documents\\Research Projects\\UMLx\\data\\Resilient Agile\\s16b_bad_driver_2018-8-19@1537423576395_analysis/EAID_2CBE2BAF_7C5E_437c_942F_B0420A261BAE/control_num_distribution_chart.svg"
  },
  {
    "column name": "entity_num",
    "statistics": {
      "mean": 0.7,
      "variance": 0.4556,
      "first_quartile": 0,
      "median": 1,
      "third_quartile": 1,
      "kurtosis": -1.1415
    },
    "dist chart path": "C:\\Users\\flyqk\\Documents\\Research Projects\\UMLx\\data\\Resilient Agile\\s16b_bad_driver_2018-8-19@1537423576395_analysis/EAID_2CBE2BAF_7C5E_437c_942F_B0420A261BAE/entity_num_distribution_chart.svg"
  },
  {
    "column name": "actor_num",
    "statistics": {
      "mean": 0,
      "variance": 0,
      "first_quartile": 0,
      "median": 0,
      "third_quartile": 0,
      "kurtosis": "NaN"
    },
    "dist chart path": "C:\\Users\\flyqk\\Documents\\Research Projects\\UMLx\\data\\Resilient Agile\\s16b_bad_driver_2018-8-19@1537423576395_analysis/EAID_2CBE2BAF_7C5E_437c_942F_B0420A261BAE/actor_num_distribution_chart.svg"
  }
] 
