[
  {
    "column name": "id",
    "statistics": {
      "mean": 9.5,
      "variance": 28.5,
      "first_quartile": 5.25,
      "median": 9.5,
      "third_quartile": 13.75,
      "kurtosis": -1.4011
    },
    "dist chart path": "H:\\ResearchSpace\\ResearchProjects\\UMLx\\data\\577 Projects\\12-22\\S14b_E-LockBox_2018-11-22@1545550013353_analysis/id_distribution_chart.svg"
  },
  {
    "column name": "NOCH",
    "statistics": {
      "mean": 0.2222,
      "variance": 0.5359,
      "first_quartile": 0,
      "median": 0,
      "third_quartile": 0,
      "kurtosis": 8.5936
    },
    "dist chart path": "H:\\ResearchSpace\\ResearchProjects\\UMLx\\data\\577 Projects\\12-22\\S14b_E-LockBox_2018-11-22@1545550013353_analysis/NOCH_distribution_chart.svg"
  },
  {
    "column name": "DIT",
    "statistics": {
      "mean": 0.2222,
      "variance": 0.5359,
      "first_quartile": 0,
      "median": 0,
      "third_quartile": 0,
      "kurtosis": 8.5936
    },
    "dist chart path": "H:\\ResearchSpace\\ResearchProjects\\UMLx\\data\\577 Projects\\12-22\\S14b_E-LockBox_2018-11-22@1545550013353_analysis/DIT_distribution_chart.svg"
  },
  {
    "column name": "CBO",
    "statistics": {
      "mean": 25.9444,
      "variance": 5459.9379,
      "first_quartile": 0,
      "median": 0,
      "third_quartile": 0,
      "kurtosis": 3.3491
    },
    "dist chart path": "H:\\ResearchSpace\\ResearchProjects\\UMLx\\data\\577 Projects\\12-22\\S14b_E-LockBox_2018-11-22@1545550013353_analysis/CBO_distribution_chart.svg"
  },
  {
    "column name": "NUMS",
    "statistics": {
      "mean": 0,
      "variance": 0,
      "first_quartile": 0,
      "median": 0,
      "third_quartile": 0,
      "kurtosis": "NaN"
    },
    "dist chart path": "H:\\ResearchSpace\\ResearchProjects\\UMLx\\data\\577 Projects\\12-22\\S14b_E-LockBox_2018-11-22@1545550013353_analysis/NUMS_distribution_chart.svg"
  },
  {
    "column name": "NCI",
    "statistics": {
      "mean": 0.2778,
      "variance": 0.9183,
      "first_quartile": 0,
      "median": 0,
      "third_quartile": 0,
      "kurtosis": 9.6706
    },
    "dist chart path": "H:\\ResearchSpace\\ResearchProjects\\UMLx\\data\\577 Projects\\12-22\\S14b_E-LockBox_2018-11-22@1545550013353_analysis/NCI_distribution_chart.svg"
  },
  {
    "column name": "NCIF",
    "statistics": {
      "mean": 0.2778,
      "variance": 0.3301,
      "first_quartile": 0,
      "median": 0,
      "third_quartile": 0,
      "kurtosis": 1.945
    },
    "dist chart path": "H:\\ResearchSpace\\ResearchProjects\\UMLx\\data\\577 Projects\\12-22\\S14b_E-LockBox_2018-11-22@1545550013353_analysis/NCIF_distribution_chart.svg"
  }
] 
