{"EstimationModel":"exucp_lm","SizeMetric":"EXUCP","TransactionMetric":"SWTII","Effort":"242.92","UseCases":[{"Name":"Call customers","_id":"EAID_7EB473B5_28A8_48a8_B696_F1E2D166D543","SizeMeasurement":"107.83","feasible":true,"Personnel_UI":"21.74%","Personnel_DB":"73.91%","Personnel_FS":"4.35%","Personnel":1,"Duration":"2.67","Effort":"139.28","useCasePMEffort":"-1.00","useCaseDEVEffort":"-1.00","synthesizedEffort":"139.28","BusinessValue":0,"BVEffortRatio":"0.00"},{"Name":"Monitor Agents","_id":"EAID_DE838191_B0F3_4f67_9F98_DC09B4EFC248","SizeMeasurement":"8.42","feasible":true,"Personnel_UI":"22.22%","Personnel_DB":"44.44%","Personnel_FS":"33.33%","Personnel":1,"Duration":"1.16","Effort":"10.87","useCasePMEffort":"-1.00","useCaseDEVEffort":"-1.00","synthesizedEffort":"10.87","BusinessValue":0,"BVEffortRatio":"0.00"},{"Name":"Receeive Calls","_id":"EAID_15F475C6_2D9C_4746_AF4C_5992AA2D0F9A","SizeMeasurement":"11.84","feasible":true,"Personnel_UI":"12.50%","Personnel_DB":"62.50%","Personnel_FS":"25.00%","Personnel":1,"Duration":"1.30","Effort":"15.30","useCasePMEffort":"-1.00","useCaseDEVEffort":"-1.00","synthesizedEffort":"15.30","BusinessValue":0,"BVEffortRatio":"0.00"},{"Name":"Record calls and call details","_id":"EAID_05F54A43_62C2_4397_96F9_AF8E21ACFC4F","SizeMeasurement":"12.78","feasible":true,"Personnel_UI":"26.67%","Personnel_DB":"26.67%","Personnel_FS":"46.67%","Personnel":1,"Duration":"1.33","Effort":"16.51","useCasePMEffort":"-1.00","useCaseDEVEffort":"-1.00","synthesizedEffort":"16.51","BusinessValue":0,"BVEffortRatio":"0.00"},{"Name":"Remove lead from auto dialer list","_id":"EAID_0A12C4C8_E91F_4bbc_8FC8_59B3905296B6","SizeMeasurement":"3.22","feasible":true,"Personnel_UI":"25.00%","Personnel_DB":"62.50%","Personnel_FS":"12.50%","Personnel":1,"Duration":"0.85","Effort":"4.16","useCasePMEffort":"-1.00","useCaseDEVEffort":"-1.00","synthesizedEffort":"4.16","BusinessValue":0,"BVEffortRatio":"0.00"},{"Name":"Request Manager Conference","_id":"EAID_493A4468_B67C_41ec_82CE_9593129A2AD3","SizeMeasurement":"16.21","feasible":true,"Personnel_UI":"26.67%","Personnel_DB":"6.67%","Personnel_FS":"66.67%","Personnel":1,"Duration":"1.44","Effort":"20.94","useCasePMEffort":"-1.00","useCaseDEVEffort":"-1.00","synthesizedEffort":"20.94","BusinessValue":0,"BVEffortRatio":"0.00"},{"Name":"Update Lead Status","_id":"EAID_72AA6ACF_774E_4425_BF65_EF52592F074F","SizeMeasurement":"3.43","feasible":true,"Personnel_UI":"28.57%","Personnel_DB":"14.29%","Personnel_FS":"57.14%","Personnel":1,"Duration":"0.86","Effort":"4.42","useCasePMEffort":"-1.00","useCaseDEVEffort":"-1.00","synthesizedEffort":"4.42","BusinessValue":0,"BVEffortRatio":"0.00"},{"Name":"View call los and listen to call recordings","_id":"EAID_103F5251_16EB_4092_9493_C4D9949C1DF1","SizeMeasurement":"24.34","feasible":true,"Personnel_UI":"12.50%","Personnel_DB":"6.25%","Personnel_FS":"81.25%","Personnel":1,"Duration":"1.64","Effort":"31.44","useCasePMEffort":"-1.00","useCaseDEVEffort":"-1.00","synthesizedEffort":"31.44","BusinessValue":0,"BVEffortRatio":"0.00"}],"DomainModel":{"MVCEstimates":{"ViewEffort":"56.06","ModelEffort":"74.75","ControlEffort":"112.12"}},"SizeMeasurement":"188.08","feasible":true,"Personnel":1,"Duration":"3.21","HoursPerMonth":152,"Personnel_UI":"21.98%","Personnel_DB":"37.15%","Personnel_FS":"40.86%","TotalSynthesizedEffort":242.92,"EstimationResultsFile":"estimationResultEXUCP.json"}