{"EstimationModel":"ducp_lm","SizeMetric":"DUCP","TransactionMetric":"SWTIII","Effort":"1.33","UseCases":[{"Name":"Forward/Rewind Video","_id":"EAID_037BFEB1_C233_43d3_8756_FE9213BB4DED","SizeMeasurement":"0.00","feasible":true,"Personnel_UI":"50.00%","Personnel_DB":"25.00%","Personnel_FS":"25.00%","Personnel":3,"Duration":"0.00","Effort":"0.00","useCasePMEffort":"-1.00","useCaseDEVEffort":"-1.00","synthesizedEffort":"0.00","BusinessValue":0,"BVEffortRatio":"0.00"},{"Name":"Open and View a certain chapter unit","_id":"EAID_9CC64295_A94C_4ee0_B772_9A5671E6D774","SizeMeasurement":"0.00","feasible":true,"Personnel_UI":"50.00%","Personnel_DB":"25.00%","Personnel_FS":"25.00%","Personnel":3,"Duration":"0.00","Effort":"0.00","useCasePMEffort":"-1.00","useCaseDEVEffort":"-1.00","synthesizedEffort":"0.00","BusinessValue":0,"BVEffortRatio":"0.00"},{"Name":"Pause Video","_id":"EAID_EBBBBBB4_2C3F_4f30_BEC2_389F4E19F89D","SizeMeasurement":"0.00","feasible":true,"Personnel_UI":"50.00%","Personnel_DB":"25.00%","Personnel_FS":"25.00%","Personnel":3,"Duration":"0.00","Effort":"0.00","useCasePMEffort":"-1.00","useCaseDEVEffort":"-1.00","synthesizedEffort":"0.00","BusinessValue":0,"BVEffortRatio":"0.00"},{"Name":"Play Video for the chapter opened","_id":"EAID_64D4C216_990B_4bfd_A703_EBAA23FBA9AC","SizeMeasurement":"0.00","feasible":true,"Personnel_UI":"50.00%","Personnel_DB":"25.00%","Personnel_FS":"25.00%","Personnel":3,"Duration":"0.00","Effort":"0.00","useCasePMEffort":"-1.00","useCaseDEVEffort":"-1.00","synthesizedEffort":"0.00","BusinessValue":0,"BVEffortRatio":"0.00"},{"Name":"Read Bill of Rights","_id":"EAID_6D7AB555_F996_4407_866F_F146EE60CF07","SizeMeasurement":"0.00","feasible":true,"Personnel_UI":"50.00%","Personnel_DB":"25.00%","Personnel_FS":"25.00%","Personnel":3,"Duration":"0.00","Effort":"0.00","useCasePMEffort":"-1.00","useCaseDEVEffort":"-1.00","synthesizedEffort":"0.00","BusinessValue":0,"BVEffortRatio":"0.00"},{"Name":"Read Welcome Message","_id":"EAID_9A67460F_A27E_44bd_8E5B_F29980C27AD1","SizeMeasurement":"0.00","feasible":true,"Personnel_UI":"50.00%","Personnel_DB":"25.00%","Personnel_FS":"25.00%","Personnel":3,"Duration":"0.00","Effort":"0.00","useCasePMEffort":"-1.00","useCaseDEVEffort":"-1.00","synthesizedEffort":"0.00","BusinessValue":0,"BVEffortRatio":"0.00"},{"Name":"Read Welcome Message","_id":"EAID_97D4F671_38D4_4137_837F_87CA8C5F3002","SizeMeasurement":"0.00","feasible":true,"Personnel_UI":"50.00%","Personnel_DB":"25.00%","Personnel_FS":"25.00%","Personnel":3,"Duration":"0.00","Effort":"0.00","useCasePMEffort":"-1.00","useCaseDEVEffort":"-1.00","synthesizedEffort":"0.00","BusinessValue":0,"BVEffortRatio":"0.00"},{"Name":"Share on twitter","_id":"EAID_6AEF37D8_841D_49f0_8649_4031E907A2BF","SizeMeasurement":"0.00","feasible":true,"Personnel_UI":"50.00%","Personnel_DB":"25.00%","Personnel_FS":"25.00%","Personnel":3,"Duration":"0.00","Effort":"0.00","useCasePMEffort":"-1.00","useCaseDEVEffort":"-1.00","synthesizedEffort":"0.00","BusinessValue":0,"BVEffortRatio":"0.00"},{"Name":"Use Case1","_id":"EAID_413ABB04_3284_4560_9038_430E34B821B2","SizeMeasurement":"0.00","feasible":true,"Personnel_UI":"50.00%","Personnel_DB":"25.00%","Personnel_FS":"25.00%","Personnel":3,"Duration":"0.00","Effort":"0.00","useCasePMEffort":"-1.00","useCaseDEVEffort":"-1.00","synthesizedEffort":"0.00","BusinessValue":0,"BVEffortRatio":"0.00"},{"Name":"Use Case2","_id":"EAID_AE0C56B8_9DF9_412a_AF50_4F5BC27CF5FC","SizeMeasurement":"0.00","feasible":true,"Personnel_UI":"50.00%","Personnel_DB":"25.00%","Personnel_FS":"25.00%","Personnel":3,"Duration":"0.00","Effort":"0.00","useCasePMEffort":"-1.00","useCaseDEVEffort":"-1.00","synthesizedEffort":"0.00","BusinessValue":0,"BVEffortRatio":"0.00"},{"Name":"View hints based on question","_id":"EAID_80533BF5_ABC5_4ab7_9B3F_E13F7728B75A","SizeMeasurement":"0.00","feasible":true,"Personnel_UI":"50.00%","Personnel_DB":"25.00%","Personnel_FS":"25.00%","Personnel":3,"Duration":"0.00","Effort":"0.00","useCasePMEffort":"-1.00","useCaseDEVEffort":"-1.00","synthesizedEffort":"0.00","BusinessValue":0,"BVEffortRatio":"0.00"},{"Name":"View table contents","_id":"EAID_015E0CB3_409A_4af4_91D0_2E49372D08D8","SizeMeasurement":"0.00","feasible":true,"Personnel_UI":"50.00%","Personnel_DB":"25.00%","Personnel_FS":"25.00%","Personnel":3,"Duration":"0.00","Effort":"0.00","useCasePMEffort":"-1.00","useCaseDEVEffort":"-1.00","synthesizedEffort":"0.00","BusinessValue":0,"BVEffortRatio":"0.00"},{"Name":"watch video in full screen","_id":"EAID_70C244D8_6BB4_4a59_B821_55EFD8EEC09D","SizeMeasurement":"0.00","feasible":true,"Personnel_UI":"50.00%","Personnel_DB":"25.00%","Personnel_FS":"25.00%","Personnel":3,"Duration":"0.00","Effort":"0.00","useCasePMEffort":"-1.00","useCaseDEVEffort":"-1.00","synthesizedEffort":"0.00","BusinessValue":0,"BVEffortRatio":"0.00"}],"DomainModel":{"MVCEstimates":{"ViewEffort":"0.00","ModelEffort":"0.00","ControlEffort":"0.00"}},"SizeMeasurement":"1.00","feasible":true,"Personnel":1,"Duration":"0.58","HoursPerMonth":152,"Personnel_UI":"50.00%","Personnel_DB":"25.00%","Personnel_FS":"25.00%","TotalSynthesizedEffort":0,"EstimationResultsFile":"estimationResultDUCP.json"}